Workbook

Sheet Parametros
A1: Parametro | B1: Valor | C1: Fuente / Nota
A2: SMLV 2026 | B2: 1750905 | C2: Salario minimo legal vigente (valor base de la planilla original)
A3: Auxilio de Transporte 2026 | B3: 249095 | C3: Valor mensual (aplica solo si IBC <= 2 SMLV)
A4: Tope Aux. Transporte (2 SMLV) | B4: =B2*2 -> 3501810 | C4: Decreto anual - Codigo Sustantivo del Trabajo Art. 7 Ley 15/1959
A5: % Aporte Salud Trabajador | B5: 0.04 | C5: Ley 100 de 1993, Art. 204
A6: % Aporte Pension Trabajador | B6: 0.04 | C6: Ley 100 de 1993, Art. 20
A7: % Aporte Salud Empleador | B7: 0.085 | C7: Ley 100 de 1993, Art. 204
A8: % Aporte Pension Empleador | B8: 0.12 | C8: Ley 100 de 1993, Art. 20
A9: % Aporte CCF Empleador | B9: 0.04 | C9: Ley 21 de 1982
A10: % Provision Cesantias (mensual) | B10: =1/12 -> 0.083333333 | C10: Un salario mensual (base+aux.transp.) por año trabajado, Ley 50 de 1990
A11: % Intereses sobre Cesantias | B11: 0.12 | C11: 12% anual sobre cesantias causadas, Ley 52 de 1975
A12: % Provision Prima (mensual) | B12: =1/12 -> 0.083333333 | C12: Un salario mensual (base+aux.transp.) por año, pagadero semestral, CST Art. 306
A13: % Provision Vacaciones | B13: 0.0417 | C13: 15 dias habiles / 360 sobre el salario base, CST Art. 186

Sheet Nomina
A1: ID EMPLEADO | B1: PRIMER APELLIDO | C1: PRIMER NOMBRE | D1: SEXO | E1: FECHA NACIMIENTO | F1: ESTADO CIVIL | G1: DEPARTAMENTO | H1: MUNICIPIO | I1: OCUPACION | J1: FECHA INGRESO | K1: FECHA RETIRO | L1: EPS | M1: AFP | N1: ARL | O1: CCF | P1: NIVEL RIESGO | Q1: IBC | R1: AUX DE TRANSPORTE | S1: DESCUENTO TRABAJADOR EPS | T1: DESCUENTO TRABAJADOR PENSION | U1: CESANTIAS | V1: INTERESES DE CESANTIAS | W1: PROVISION PRIMA | X1: PROVISION VACACIONES | Y1: APORTE SALUD EMPLEADOR 8,5% | Z1: APORTE PENSION EMPLEADOR 12% | AA1: APORTE EMPLEADOR CCF | AB1: APORTE EMPLEADOR ARL
A2: EMP-001 | B2: Ortiz | C2: Oscar | D2: M | E2: 33486 | F2: Soltero | G2: Bogotá D.C | H2: Bogotá | I2: AUXILIAR DE BODEGA | J2: 46082 | L2: SALUD TOTAL | M2: PORVENIR S.A. | N2: ARL SURA | O2: COLSUBSIDIO | P2: 0.0435 | Q2: 1750905 | R2: =IF(Q2<=Parametros!$B$4,Parametros!$B$3,0) -> 249095 | S2: =Q2*Parametros!$B$5 -> 70036.2 | T2: =Q2*Parametros!$B$6 -> 70036.2 | U2: =(Q2+R2)*Parametros!$B$10 -> 166666.67 | V2: =U2*Parametros!$B$11 -> 20000 | W2: =(Q2+R2)*Parametros!$B$12 -> 166666.67 | X2: =Q2*Parametros!$B$13 -> 73012.739 | Y2: =Q2*Parametros!$B$7 -> 148826.92 | Z2: =Q2*Parametros!$B$8 -> 210108.6 | AA2: =Q2*Parametros!$B$9 -> 70036.2 | AB2: =Q2*P2 -> 76164.367
A3: EMP-002 | B3: Alvarez | C3: Jorge | D3: M | E3: 28106 | F3: Soltero | G3: Bogotá D.C | H3: Bogotá | I3: ANALISTA DE INVENTARIOS | J3: 44838 | L3: SALUD TOTAL | M3: PORVENIR S.A. | N3: ARL SURA | O3: COLSUBSIDIO | P3: 0.00522 | Q3: 1750905 | R3: =IF(Q3<=Parametros!$B$4,Parametros!$B$3,0) -> 249095 | S3: =Q3*Parametros!$B$5 -> 70036.2 | T3: =Q3*Parametros!$B$6 -> 70036.2 | U3: =(Q3+R3)*Parametros!$B$10 -> 166666.67 | V3: =U3*Parametros!$B$11 -> 20000 | W3: =(Q3+R3)*Parametros!$B$12 -> 166666.67 | X3: =Q3*Parametros!$B$13 -> 73012.739 | Y3: =Q3*Parametros!$B$7 -> 148826.92 | Z3: =Q3*Parametros!$B$8 -> 210108.6 | AA3: =Q3*Parametros!$B$9 -> 70036.2 | AB3: =Q3*P3 -> 9139.7241
A4: EMP-003 | B4: Ramirez | C4: Sergio | D4: M | E4: 32609 | F4: Soltero | G4: Bogotá D.C | H4: Bogotá | I4: AUXILIAR DE BODEGA | J4: 44958 | L4: SURA EPS | M4: PROTECCION | N4: ARL SURA | O4: COLSUBSIDIO | P4: 0.0435 | Q4: 1750905 | R4: =IF(Q4<=Parametros!$B$4,Parametros!$B$3,0) -> 249095 | S4: =Q4*Parametros!$B$5 -> 70036.2 | T4: =Q4*Parametros!$B$6 -> 70036.2 | U4: =(Q4+R4)*Parametros!$B$10 -> 166666.67 | V4: =U4*Parametros!$B$11 -> 20000 | W4: =(Q4+R4)*Parametros!$B$12 -> 166666.67 | X4: =Q4*Parametros!$B$13 -> 73012.739 | Y4: =Q4*Parametros!$B$7 -> 148826.92 | Z4: =Q4*Parametros!$B$8 -> 210108.6 | AA4: =Q4*Parametros!$B$9 -> 70036.2 | AB4: =Q4*P4 -> 76164.367
A5: EMP-004 | B5: Moreno | C5: Johana | D5: F | E5: 32736 | F5: Soltero | G5: Bogotá D.C | H5: Bogotá | I5: AUXILIAR DE BODEGA | J5: 45597 | L5: COMPENSAR EPS | M5: COLPENSIONES | N5: ARL SURA | O5: COLSUBSIDIO | P5: 0.0435 | Q5: 1750905 | R5: =IF(Q5<=Parametros!$B$4,Parametros!$B$3,0) -> 249095 | S5: =Q5*Parametros!$B$5 -> 70036.2 | T5: =Q5*Parametros!$B$6 -> 70036.2 | U5: =(Q5+R5)*Parametros!$B$10 -> 166666.67 | V5: =U5*Parametros!$B$11 -> 20000 | W5: =(Q5+R5)*Parametros!$B$12 -> 166666.67 | X5: =Q5*Parametros!$B$13 -> 73012.739 | Y5: =Q5*Parametros!$B$7 -> 148826.92 | Z5: =Q5*Parametros!$B$8 -> 210108.6 | AA5: =Q5*Parametros!$B$9 -> 70036.2 | AB5: =Q5*P5 -> 76164.367
A6: EMP-005 | B6: Mendoza | C6: Laura | D6: F | E6: 34029 | F6: Soltero | G6: Bogotá D.C | H6: Bogotá | I6: AUXILIAR DE BODEGA | J6: 45726 | L6: COMPENSAR EPS | M6: PORVENIR S.A. | N6: ARL SURA | O6: COMPENSAR | P6: 0.0435 | Q6: 1750905 | R6: =IF(Q6<=Parametros!$B$4,Parametros!$B$3,0) -> 249095 | S6: =Q6*Parametros!$B$5 -> 70036.2 | T6: =Q6*Parametros!$B$6 -> 70036.2 | U6: =(Q6+R6)*Parametros!$B$10 -> 166666.67 | V6: =U6*Parametros!$B$11 -> 20000 | W6: =(Q6+R6)*Parametros!$B$12 -> 166666.67 | X6: =Q6*Parametros!$B$13 -> 73012.739 | Y6: =Q6*Parametros!$B$7 -> 148826.92 | Z6: =Q6*Parametros!$B$8 -> 210108.6 | AA6: =Q6*Parametros!$B$9 -> 70036.2 | AB6: =Q6*P6 -> 76164.367
A7: EMP-006 | B7: Mendoza | C7: Juan | D7: M | E7: 31492 | F7: Soltero | G7: Bogotá D.C | H7: Bogotá | I7: AUXILIAR DE BODEGA | J7: 45866 | L7: SANITAS | M7: PROTECCION | N7: ARL SURA | O7: COLSUBSIDIO | P7: 0.0435 | Q7: 1750905 | R7: =IF(Q7<=Parametros!$B$4,Parametros!$B$3,0) -> 249095 | S7: =Q7*Parametros!$B$5 -> 70036.2 | T7: =Q7*Parametros!$B$6 -> 70036.2 | U7: =(Q7+R7)*Parametros!$B$10 -> 166666.67 | V7: =U7*Parametros!$B$11 -> 20000 | W7: =(Q7+R7)*Parametros!$B$12 -> 166666.67 | X7: =Q7*Parametros!$B$13 -> 73012.739 | Y7: =Q7*Parametros!$B$7 -> 148826.92 | Z7: =Q7*Parametros!$B$8 -> 210108.6 | AA7: =Q7*Parametros!$B$9 -> 70036.2 | AB7: =Q7*P7 -> 76164.367
A8: EMP-007 | B8: Cardenas | C8: Gloria | D8: F | E8: 28718 | F8: Soltero | G8: Bogotá D.C | H8: Bogotá | I8: AUXILIAR DE BODEGA | J8: 45058 | L8: COMPENSAR EPS | M8: PROTECCION | N8: ARL SURA | O8: COLSUBSIDIO | P8: 0.0435 | Q8: 1750905 | R8: =IF(Q8<=Parametros!$B$4,Parametros!$B$3,0) -> 249095 | S8: =Q8*Parametros!$B$5 -> 70036.2 | T8: =Q8*Parametros!$B$6 -> 70036.2 | U8: =(Q8+R8)*Parametros!$B$10 -> 166666.67 | V8: =U8*Parametros!$B$11 -> 20000 | W8: =(Q8+R8)*Parametros!$B$12 -> 166666.67 | X8: =Q8*Parametros!$B$13 -> 73012.739 | Y8: =Q8*Parametros!$B$7 -> 148826.92 | Z8: =Q8*Parametros!$B$8 -> 210108.6 | AA8: =Q8*Parametros!$B$9 -> 70036.2 | AB8: =Q8*P8 -> 76164.367
A9: EMP-008 | B9: Hernandez | C9: Alejandro | D9: M | E9: 31878 | F9: Soltero | G9: Bogotá D.C | H9: Bogotá | I9: ASESOR COMERCIAL | J9: 44256 | L9: COMPENSAR EPS | M9: PORVENIR S.A. | N9: ARL SURA | O9: COLSUBSIDIO | P9: 0.00522 | Q9: 2000000 | R9: =IF(Q9<=Parametros!$B$4,Parametros!$B$3,0) -> 249095 | S9: =Q9*Parametros!$B$5 -> 80000 | T9: =Q9*Parametros!$B$6 -> 80000 | U9: =(Q9+R9)*Parametros!$B$10 -> 187424.58 | V9: =U9*Parametros!$B$11 -> 22490.95 | W9: =(Q9+R9)*Parametros!$B$12 -> 187424.58 | X9: =Q9*Parametros!$B$13 -> 83400 | Y9: =Q9*Parametros!$B$7 -> 170000 | Z9: =Q9*Parametros!$B$8 -> 240000 | AA9: =Q9*Parametros!$B$9 -> 80000 | AB9: =Q9*P9 -> 10440
A10: EMP-009 | B10: Diaz | C10: Luis | D10: M | E10: 28492 | F10: Soltero | G10: Bogotá D.C | H10: Bogotá | I10: ASESOR COMERCIAL | J10: 46167 | K10: 46174 | L10: FAMISANAR | M10: COLFONDOS | N10: ARL SURA | O10: COLSUBSIDIO | P10: 0.00522 | Q10: 2000000 | R10: =IF(Q10<=Parametros!$B$4,Parametros!$B$3,0) -> 249095 | S10: =Q10*Parametros!$B$5 -> 80000 | T10: =Q10*Parametros!$B$6 -> 80000 | U10: =(Q10+R10)*Parametros!$B$10 -> 187424.58 | V10: =U10*Parametros!$B$11 -> 22490.95 | W10: =(Q10+R10)*Parametros!$B$12 -> 187424.58 | X10: =Q10*Parametros!$B$13 -> 83400 | Y10: =Q10*Parametros!$B$7 -> 170000 | Z10: =Q10*Parametros!$B$8 -> 240000 | AA10: =Q10*Parametros!$B$9 -> 80000 | AB10: =Q10*P10 -> 10440
A11: EMP-010 | B11: Cruz | C11: Catalina | D11: F | E11: 32384 | F11: Soltero | G11: Bogotá D.C | H11: Bogotá | I11: ASESOR COMERCIAL | J11: 46014 | L11: FAMISANAR | M11: PORVENIR S.A. | N11: ARL SURA | O11: COLSUBSIDIO | P11: 0.00522 | Q11: 2000000 | R11: =IF(Q11<=Parametros!$B$4,Parametros!$B$3,0) -> 249095 | S11: =Q11*Parametros!$B$5 -> 80000 | T11: =Q11*Parametros!$B$6 -> 80000 | U11: =(Q11+R11)*Parametros!$B$10 -> 187424.58 | V11: =U11*Parametros!$B$11 -> 22490.95 | W11: =(Q11+R11)*Parametros!$B$12 -> 187424.58 | X11: =Q11*Parametros!$B$13 -> 83400 | Y11: =Q11*Parametros!$B$7 -> 170000 | Z11: =Q11*Parametros!$B$8 -> 240000 | AA11: =Q11*Parametros!$B$9 -> 80000 | AB11: =Q11*P11 -> 10440
A12: EMP-011 | B12: Mendoza | C12: David | D12: M | E12: 26527 | F12: Soltero | G12: Bogotá D.C | H12: Bogotá | I12: ASESOR COMERCIAL | J12: 45413 | L12: COMPENSAR EPS | M12: PORVENIR S.A. | N12: ARL SURA | O12: COLSUBSIDIO | P12: 0.00522 | Q12: 2000000 | R12: =IF(Q12<=Parametros!$B$4,Parametros!$B$3,0) -> 249095 | S12: =Q12*Parametros!$B$5 -> 80000 | T12: =Q12*Parametros!$B$6 -> 80000 | U12: =(Q12+R12)*Parametros!$B$10 -> 187424.58 | V12: =U12*Parametros!$B$11 -> 22490.95 | W12: =(Q12+R12)*Parametros!$B$12 -> 187424.58 | X12: =Q12*Parametros!$B$13 -> 83400 | Y12: =Q12*Parametros!$B$7 -> 170000 | Z12: =Q12*Parametros!$B$8 -> 240000 | AA12: =Q12*Parametros!$B$9 -> 80000 | AB12: =Q12*P12 -> 10440
A13: EMP-012 | B13: Duque | C13: Andres | D13: M | E13: 28878 | F13: Soltero | G13: Cundinamarca | H13: SOACHA | I13: ASESOR COMERCIAL | J13: 45383 | L13: SANITAS | M13: COLFONDOS | N13: ARL SURA | O13: COLSUBSIDIO | P13: 0.00522 | Q13: 2000000 | R13: =IF(Q13<=Parametros!$B$4,Parametros!$B$3,0) -> 249095 | S13: =Q13*Parametros!$B$5 -> 80000 | T13: =Q13*Parametros!$B$6 -> 80000 | U13: =(Q13+R13)*Parametros!$B$10 -> 187424.58 | V13: =U13*Parametros!$B$11 -> 22490.95 | W13: =(Q13+R13)*Parametros!$B$12 -> 187424.58 | X13: =Q13*Parametros!$B$13 -> 83400 | Y13: =Q13*Parametros!$B$7 -> 170000 | Z13: =Q13*Parametros!$B$8 -> 240000 | AA13: =Q13*Parametros!$B$9 -> 80000 | AB13: =Q13*P13 -> 10440
A14: EMP-013 | B14: Jimenez | C14: Lorena | D14: F | E14: 28595 | F14: Soltero | G14: Bogotá D.C | H14: Bogotá | I14: CONDUCTOR | J14: 45932 | L14: SANITAS | M14: PROTECCION | N14: ARL SURA | O14: COLSUBSIDIO | P14: 0.0696 | Q14: 1900000 | R14: =IF(Q14<=Parametros!$B$4,Parametros!$B$3,0) -> 249095 | S14: =Q14*Parametros!$B$5 -> 76000 | T14: =Q14*Parametros!$B$6 -> 76000 | U14: =(Q14+R14)*Parametros!$B$10 -> 179091.25 | V14: =U14*Parametros!$B$11 -> 21490.95 | W14: =(Q14+R14)*Parametros!$B$12 -> 179091.25 | X14: =Q14*Parametros!$B$13 -> 79230 | Y14: =Q14*Parametros!$B$7 -> 161500 | Z14: =Q14*Parametros!$B$8 -> 228000 | AA14: =Q14*Parametros!$B$9 -> 76000 | AB14: =Q14*P14 -> 132240
A15: EMP-014 | B15: Ramirez | C15: Mauricio | D15: M | E15: 27760 | F15: Soltero | G15: Bogotá D.C | H15: Bogotá | I15: CONDUCTOR | J15: 45993 | L15: FAMISANAR | M15: PORVENIR S.A. | N15: ARL SURA | O15: COLSUBSIDIO | P15: 0.0696 | Q15: 1900000 | R15: =IF(Q15<=Parametros!$B$4,Parametros!$B$3,0) -> 249095 | S15: =Q15*Parametros!$B$5 -> 76000 | T15: =Q15*Parametros!$B$6 -> 76000 | U15: =(Q15+R15)*Parametros!$B$10 -> 179091.25 | V15: =U15*Parametros!$B$11 -> 21490.95 | W15: =(Q15+R15)*Parametros!$B$12 -> 179091.25 | X15: =Q15*Parametros!$B$13 -> 79230 | Y15: =Q15*Parametros!$B$7 -> 161500 | Z15: =Q15*Parametros!$B$8 -> 228000 | AA15: =Q15*Parametros!$B$9 -> 76000 | AB15: =Q15*P15 -> 132240
A16: EMP-015 | B16: Rivera | C16: Diego | D16: M | E16: 30068 | F16: Soltero | G16: Bogotá D.C | H16: Bogotá | I16: AUXILIAR DE BODEGA | J16: 43826 | L16: SANITAS | M16: COLPENSIONES | N16: ARL SURA | O16: COLSUBSIDIO | P16: 0.0435 | Q16: 1750905 | R16: =IF(Q16<=Parametros!$B$4,Parametros!$B$3,0) -> 249095 | S16: =Q16*Parametros!$B$5 -> 70036.2 | T16: =Q16*Parametros!$B$6 -> 70036.2 | U16: =(Q16+R16)*Parametros!$B$10 -> 166666.67 | V16: =U16*Parametros!$B$11 -> 20000 | W16: =(Q16+R16)*Parametros!$B$12 -> 166666.67 | X16: =Q16*Parametros!$B$13 -> 73012.739 | Y16: =Q16*Parametros!$B$7 -> 148826.92 | Z16: =Q16*Parametros!$B$8 -> 210108.6 | AA16: =Q16*Parametros!$B$9 -> 70036.2 | AB16: =Q16*P16 -> 76164.367
A17: EMP-016 | B17: Duque | C17: Andres | D17: M | E17: 27743 | F17: Soltero | G17: Bogotá D.C | H17: Bogotá | I17: CONDUCTOR | J17: 46217 | L17: SALUD TOTAL | M17: PROTECCION | N17: ARL SURA | O17: COLSUBSIDIO | P17: 0.0696 | Q17: 1900000 | R17: =IF(Q17<=Parametros!$B$4,Parametros!$B$3,0) -> 249095 | S17: =Q17*Parametros!$B$5 -> 76000 | T17: =Q17*Parametros!$B$6 -> 76000 | U17: =(Q17+R17)*Parametros!$B$10 -> 179091.25 | V17: =U17*Parametros!$B$11 -> 21490.95 | W17: =(Q17+R17)*Parametros!$B$12 -> 179091.25 | X17: =Q17*Parametros!$B$13 -> 79230 | Y17: =Q17*Parametros!$B$7 -> 161500 | Z17: =Q17*Parametros!$B$8 -> 228000 | AA17: =Q17*Parametros!$B$9 -> 76000 | AB17: =Q17*P17 -> 132240
A18: EMP-017 | B18: Jimenez | C18: Juan | D18: M | E18: 28024 | F18: Soltero | G18: Bogotá D.C | H18: Bogotá | I18: AUXILIAR DE BODEGA | J18: 46056 | L18: FAMISANAR | M18: PROTECCION | N18: ARL SURA | O18: COMPENSAR | P18: 0.0435 | Q18: 1750905 | R18: =IF(Q18<=Parametros!$B$4,Parametros!$B$3,0) -> 249095 | S18: =Q18*Parametros!$B$5 -> 70036.2 | T18: =Q18*Parametros!$B$6 -> 70036.2 | U18: =(Q18+R18)*Parametros!$B$10 -> 166666.67 | V18: =U18*Parametros!$B$11 -> 20000 | W18: =(Q18+R18)*Parametros!$B$12 -> 166666.67 | X18: =Q18*Parametros!$B$13 -> 73012.739 | Y18: =Q18*Parametros!$B$7 -> 148826.92 | Z18: =Q18*Parametros!$B$8 -> 210108.6 | AA18: =Q18*Parametros!$B$9 -> 70036.2 | AB18: =Q18*P18 -> 76164.367
A19: EMP-018 | B19: Silva | C19: Monica | D19: F | E19: 30377 | F19: Soltero | G19: Bogotá D.C | H19: Bogotá | I19: ASESOR COMERCIAL | J19: 46029 | L19: SANITAS | M19: PROTECCION | N19: ARL SURA | O19: COLSUBSIDIO | P19: 0.00522 | Q19: 2000000 | R19: =IF(Q19<=Parametros!$B$4,Parametros!$B$3,0) -> 249095 | S19: =Q19*Parametros!$B$5 -> 80000 | T19: =Q19*Parametros!$B$6 -> 80000 | U19: =(Q19+R19)*Parametros!$B$10 -> 187424.58 | V19: =U19*Parametros!$B$11 -> 22490.95 | W19: =(Q19+R19)*Parametros!$B$12 -> 187424.58 | X19: =Q19*Parametros!$B$13 -> 83400 | Y19: =Q19*Parametros!$B$7 -> 170000 | Z19: =Q19*Parametros!$B$8 -> 240000 | AA19: =Q19*Parametros!$B$9 -> 80000 | AB19: =Q19*P19 -> 10440
A20: EMP-019 | B20: Castillo | C20: Julian | D20: M | E20: 30016 | F20: Soltero | G20: Bogotá D.C | H20: Bogotá | I20: CONDUCTOR | J20: 46113 | L20: SALUD TOTAL | M20: PROTECCION | N20: ARL SURA | O20: COLSUBSIDIO | P20: 0.0696 | Q20: 1900000 | R20: =IF(Q20<=Parametros!$B$4,Parametros!$B$3,0) -> 249095 | S20: =Q20*Parametros!$B$5 -> 76000 | T20: =Q20*Parametros!$B$6 -> 76000 | U20: =(Q20+R20)*Parametros!$B$10 -> 179091.25 | V20: =U20*Parametros!$B$11 -> 21490.95 | W20: =(Q20+R20)*Parametros!$B$12 -> 179091.25 | X20: =Q20*Parametros!$B$13 -> 79230 | Y20: =Q20*Parametros!$B$7 -> 161500 | Z20: =Q20*Parametros!$B$8 -> 228000 | AA20: =Q20*Parametros!$B$9 -> 76000 | AB20: =Q20*P20 -> 132240
A21: EMP-020 | B21: Nunez | C21: Juan | D21: M | E21: 26594 | F21: Soltero | G21: Bogotá D.C | H21: Bogotá | I21: AUXILIAR ADMINISTRATIVO | J21: 45383 | L21: FAMISANAR | M21: COLPENSIONES | N21: ARL SURA | O21: COLSUBSIDIO | P21: 0.00522 | Q21: 1750905 | R21: =IF(Q21<=Parametros!$B$4,Parametros!$B$3,0) -> 249095 | S21: =Q21*Parametros!$B$5 -> 70036.2 | T21: =Q21*Parametros!$B$6 -> 70036.2 | U21: =(Q21+R21)*Parametros!$B$10 -> 166666.67 | V21: =U21*Parametros!$B$11 -> 20000 | W21: =(Q21+R21)*Parametros!$B$12 -> 166666.67 | X21: =Q21*Parametros!$B$13 -> 73012.739 | Y21: =Q21*Parametros!$B$7 -> 148826.92 | Z21: =Q21*Parametros!$B$8 -> 210108.6 | AA21: =Q21*Parametros!$B$9 -> 70036.2 | AB21: =Q21*P21 -> 9139.7241
A22: EMP-021 | B22: Rojas | C22: Santiago | D22: M | E22: 29940 | F22: Soltero | G22: Bogotá D.C | H22: Bogotá | I22: CONDUCTOR | J22: 46204 | L22: SANITAS | M22: PORVENIR S.A. | N22: ARL SURA | O22: COLSUBSIDIO | P22: 0.0696 | Q22: 1900000 | R22: =IF(Q22<=Parametros!$B$4,Parametros!$B$3,0) -> 249095 | S22: =Q22*Parametros!$B$5 -> 76000 | T22: =Q22*Parametros!$B$6 -> 76000 | U22: =(Q22+R22)*Parametros!$B$10 -> 179091.25 | V22: =U22*Parametros!$B$11 -> 21490.95 | W22: =(Q22+R22)*Parametros!$B$12 -> 179091.25 | X22: =Q22*Parametros!$B$13 -> 79230 | Y22: =Q22*Parametros!$B$7 -> 161500 | Z22: =Q22*Parametros!$B$8 -> 228000 | AA22: =Q22*Parametros!$B$9 -> 76000 | AB22: =Q22*P22 -> 132240
... A42: EMP-041 | B42: Herrera | C42: Leonardo | D42: M | E42: 26660 | F42: Soltero | G42: Bogotá D.C | H42: Bogotá | I42: AUXILIAR CONTABLE | J42: 46177 | L42: SALUD TOTAL | M42: PORVENIR S.A. | N42: ARL SURA | O42: COLSUBSIDIO | P42: 0.00522 | Q42: 1750905 | R42: =IF(Q42<=Parametros!$B$4,Parametros!$B$3,0) -> 249095 | S42: =Q42*Parametros!$B$5 -> 70036.2 | T42: =Q42*Parametros!$B$6 -> 70036.2 | U42: =(Q42+R42)*Parametros!$B$10 -> 166666.67 | V42: =U42*Parametros!$B$11 -> 20000 | W42: =(Q42+R42)*Parametros!$B$12 -> 166666.67 | X42: =Q42*Parametros!$B$13 -> 73012.739 | Y42: =Q42*Parametros!$B$7 -> 148826.92 | Z42: =Q42*Parametros!$B$8 -> 210108.6 | AA42: =Q42*Parametros!$B$9 -> 70036.2 | AB42: =Q42*P42 -> 9139.7241
A43: EMP-042 | B43: Ramirez | C43: Jorge | D43: M | E43: 27095 | F43: Soltero | G43: Bogotá D.C | H43: Bogotá | I43: AUXILIAR DE BODEGA | J43: 46097 | K43: 46143 | L43: SANITAS | M43: COLPENSIONES | N43: ARL SURA | O43: COLSUBSIDIO | P43: 0.0435 | Q43: 1750905 | R43: =IF(Q43<=Parametros!$B$4,Parametros!$B$3,0) -> 249095 | S43: =Q43*Parametros!$B$5 -> 70036.2 | T43: =Q43*Parametros!$B$6 -> 70036.2 | U43: =(Q43+R43)*Parametros!$B$10 -> 166666.67 | V43: =U43*Parametros!$B$11 -> 20000 | W43: =(Q43+R43)*Parametros!$B$12 -> 166666.67 | X43: =Q43*Parametros!$B$13 -> 73012.739 | Y43: =Q43*Parametros!$B$7 -> 148826.92 | Z43: =Q43*Parametros!$B$8 -> 210108.6 | AA43: =Q43*Parametros!$B$9 -> 70036.2 | AB43: =Q43*P43 -> 76164.367
A44: EMP-043 | B44: Bautista | C44: Ricardo | D44: M | E44: 25900 | F44: Soltero | G44: Cundinamarca | H44: MOSQUERA | I44: CONDUCTOR | J44: 45717 | L44: FAMISANAR | M44: PORVENIR S.A. | N44: ARL SURA | O44: COLSUBSIDIO | P44: 0.0696 | Q44: 1900000 | R44: =IF(Q44<=Parametros!$B$4,Parametros!$B$3,0) -> 249095 | S44: =Q44*Parametros!$B$5 -> 76000 | T44: =Q44*Parametros!$B$6 -> 76000 | U44: =(Q44+R44)*Parametros!$B$10 -> 179091.25 | V44: =U44*Parametros!$B$11 -> 21490.95 | W44: =(Q44+R44)*Parametros!$B$12 -> 179091.25 | X44: =Q44*Parametros!$B$13 -> 79230 | Y44: =Q44*Parametros!$B$7 -> 161500 | Z44: =Q44*Parametros!$B$8 -> 228000 | AA44: =Q44*Parametros!$B$9 -> 76000 | AB44: =Q44*P44 -> 132240
A45: EMP-044 | B45: Aguirre | C45: Julian | D45: M | E45: 33746 | F45: Soltero | G45: Bogotá D.C | H45: Bogotá | I45: AUXILIAR DE BODEGA | J45: 44562 | L45: COMPENSAR EPS | M45: PROTECCION | N45: ARL SURA | O45: COLSUBSIDIO | P45: 0.0435 | Q45: 1750905 | R45: =IF(Q45<=Parametros!$B$4,Parametros!$B$3,0) -> 249095 | S45: =Q45*Parametros!$B$5 -> 70036.2 | T45: =Q45*Parametros!$B$6 -> 70036.2 | U45: =(Q45+R45)*Parametros!$B$10 -> 166666.67 | V45: =U45*Parametros!$B$11 -> 20000 | W45: =(Q45+R45)*Parametros!$B$12 -> 166666.67 | X45: =Q45*Parametros!$B$13 -> 73012.739 | Y45: =Q45*Parametros!$B$7 -> 148826.92 | Z45: =Q45*Parametros!$B$8 -> 210108.6 | AA45: =Q45*Parametros!$B$9 -> 70036.2 | AB45: =Q45*P45 -> 76164.367
A46: EMP-045 | B46: Lopez | C46: Paula | D46: F | E46: 35759 | F46: Soltero | G46: Bogotá D.C | H46: Bogotá | I46: AUXILIAR DE BODEGA | J46: 45931 | L46: SANITAS | M46: COLPENSIONES | N46: ARL SURA | O46: COLSUBSIDIO | P46: 0.0435 | Q46: 1750905 | R46: =IF(Q46<=Parametros!$B$4,Parametros!$B$3,0) -> 249095 | S46: =Q46*Parametros!$B$5 -> 70036.2 | T46: =Q46*Parametros!$B$6 -> 70036.2 | U46: =(Q46+R46)*Parametros!$B$10 -> 166666.67 | V46: =U46*Parametros!$B$11 -> 20000 | W46: =(Q46+R46)*Parametros!$B$12 -> 166666.67 | X46: =Q46*Parametros!$B$13 -> 73012.739 | Y46: =Q46*Parametros!$B$7 -> 148826.92 | Z46: =Q46*Parametros!$B$8 -> 210108.6 | AA46: =Q46*Parametros!$B$9 -> 70036.2 | AB46: =Q46*P46 -> 76164.367
A47: EMP-046 | B47: Ospina | C47: Alejandro | D47: M | E47: 28044 | F47: Soltero | G47: Bogotá D.C | H47: Bogotá | I47: CONDUCTOR | J47: 45870 | L47: SURA EPS | M47: COLPENSIONES | N47: ARL SURA | O47: COLSUBSIDIO | P47: 0.0696 | Q47: 1900000 | R47: =IF(Q47<=Parametros!$B$4,Parametros!$B$3,0) -> 249095 | S47: =Q47*Parametros!$B$5 -> 76000 | T47: =Q47*Parametros!$B$6 -> 76000 | U47: =(Q47+R47)*Parametros!$B$10 -> 179091.25 | V47: =U47*Parametros!$B$11 -> 21490.95 | W47: =(Q47+R47)*Parametros!$B$12 -> 179091.25 | X47: =Q47*Parametros!$B$13 -> 79230 | Y47: =Q47*Parametros!$B$7 -> 161500 | Z47: =Q47*Parametros!$B$8 -> 228000 | AA47: =Q47*Parametros!$B$9 -> 76000 | AB47: =Q47*P47 -> 132240
A48: EMP-047 | B48: Duque | C48: Diana | D48: F | E48: 27442 | F48: Soltero | G48: Bogotá D.C | H48: Bogotá | I48: SUPERVISOR DE BODEGA | J48: 45400 | L48: FAMISANAR | M48: PORVENIR S.A. | N48: ARL SURA | O48: COLSUBSIDIO | P48: 0.0435 | Q48: 2600000 | R48: =IF(Q48<=Parametros!$B$4,Parametros!$B$3,0) -> 249095 | S48: =Q48*Parametros!$B$5 -> 104000 | T48: =Q48*Parametros!$B$6 -> 104000 | U48: =(Q48+R48)*Parametros!$B$10 -> 237424.58 | V48: =U48*Parametros!$B$11 -> 28490.95 | W48: =(Q48+R48)*Parametros!$B$12 -> 237424.58 | X48: =Q48*Parametros!$B$13 -> 108420 | Y48: =Q48*Parametros!$B$7 -> 221000 | Z48: =Q48*Parametros!$B$8 -> 312000 | AA48: =Q48*Parametros!$B$9 -> 104000 | AB48: =Q48*P48 -> 113100
A49: EMP-048 | B49: Mendoza | C49: David | D49: M | E49: 33589 | F49: Soltero | G49: Bogotá D.C | H49: Bogotá | I49: AUXILIAR ADMINISTRATIVO | J49: 45413 | L49: SANITAS | M49: COLPENSIONES | N49: ARL SURA | O49: COLSUBSIDIO | P49: 0.00522 | Q49: 1750905 | R49: =IF(Q49<=Parametros!$B$4,Parametros!$B$3,0) -> 249095 | S49: =Q49*Parametros!$B$5 -> 70036.2 | T49: =Q49*Parametros!$B$6 -> 70036.2 | U49: =(Q49+R49)*Parametros!$B$10 -> 166666.67 | V49: =U49*Parametros!$B$11 -> 20000 | W49: =(Q49+R49)*Parametros!$B$12 -> 166666.67 | X49: =Q49*Parametros!$B$13 -> 73012.739 | Y49: =Q49*Parametros!$B$7 -> 148826.92 | Z49: =Q49*Parametros!$B$8 -> 210108.6 | AA49: =Q49*Parametros!$B$9 -> 70036.2 | AB49: =Q49*P49 -> 9139.7241
A50: EMP-049 | B50: Mendoza | C50: Claudia | D50: F | E50: 33960 | F50: Soltero | G50: Bogotá D.C | H50: Bogotá | I50: ANALISTA DE RUTAS | J50: 46230 | L50: SALUD TOTAL | M50: PORVENIR S.A. | N50: ARL SURA | O50: COLSUBSIDIO | P50: 0.00522 | Q50: 1750905 | R50: =IF(Q50<=Parametros!$B$4,Parametros!$B$3,0) -> 249095 | S50: =Q50*Parametros!$B$5 -> 70036.2 | T50: =Q50*Parametros!$B$6 -> 70036.2 | U50: =(Q50+R50)*Parametros!$B$10 -> 166666.67 | V50: =U50*Parametros!$B$11 -> 20000 | W50: =(Q50+R50)*Parametros!$B$12 -> 166666.67 | X50: =Q50*Parametros!$B$13 -> 73012.739 | Y50: =Q50*Parametros!$B$7 -> 148826.92 | Z50: =Q50*Parametros!$B$8 -> 210108.6 | AA50: =Q50*Parametros!$B$9 -> 70036.2 | AB50: =Q50*P50 -> 9139.7241
A51: EMP-050 | B51: Mendoza | C51: Alejandro | D51: M | E51: 32071 | F51: Soltero | G51: Bogotá D.C | H51: Bogotá | I51: AUXILIAR DE BODEGA | J51: 46027 | L51: FAMISANAR | M51: PROTECCION | N51: ARL SURA | O51: COLSUBSIDIO | P51: 0.0435 | Q51: 1750905 | R51: =IF(Q51<=Parametros!$B$4,Parametros!$B$3,0) -> 249095 | S51: =Q51*Parametros!$B$5 -> 70036.2 | T51: =Q51*Parametros!$B$6 -> 70036.2 | U51: =(Q51+R51)*Parametros!$B$10 -> 166666.67 | V51: =U51*Parametros!$B$11 -> 20000 | W51: =(Q51+R51)*Parametros!$B$12 -> 166666.67 | X51: =Q51*Parametros!$B$13 -> 73012.739 | Y51: =Q51*Parametros!$B$7 -> 148826.92 | Z51: =Q51*Parametros!$B$8 -> 210108.6 | AA51: =Q51*Parametros!$B$9 -> 70036.2 | AB51: =Q51*P51 -> 76164.367
A52: EMP-051 | B52: Mendoza | C52: Fernando | D52: M | E52: 28584 | F52: Soltero | G52: Cundinamarca | H52: SOACHA | I52: AUXILIAR CONTABLE | J52: 43497 | L52: SANITAS | M52: PORVENIR S.A. | N52: ARL SURA | O52: COLSUBSIDIO | P52: 0.00522 | Q52: 1750905 | R52: =IF(Q52<=Parametros!$B$4,Parametros!$B$3,0) -> 249095 | S52: =Q52*Parametros!$B$5 -> 70036.2 | T52: =Q52*Parametros!$B$6 -> 70036.2 | U52: =(Q52+R52)*Parametros!$B$10 -> 166666.67 | V52: =U52*Parametros!$B$11 -> 20000 | W52: =(Q52+R52)*Parametros!$B$12 -> 166666.67 | X52: =Q52*Parametros!$B$13 -> 73012.739 | Y52: =Q52*Parametros!$B$7 -> 148826.92 | Z52: =Q52*Parametros!$B$8 -> 210108.6 | AA52: =Q52*Parametros!$B$9 -> 70036.2 | AB52: =Q52*P52 -> 9139.7241
A53: EMP-052 | B53: Perez | C53: Gustavo | D53: M | E53: 27695 | F53: Soltero | G53: Cundinamarca | H53: SOACHA | I53: ANALISTA DE INVENTARIOS | J53: 45794 | L53: FAMISANAR | M53: PORVENIR S.A. | N53: ARL SURA | O53: COLSUBSIDIO | P53: 0.00522 | Q53: 1750905 | R53: =IF(Q53<=Parametros!$B$4,Parametros!$B$3,0) -> 249095 | S53: =Q53*Parametros!$B$5 -> 70036.2 | T53: =Q53*Parametros!$B$6 -> 70036.2 | U53: =(Q53+R53)*Parametros!$B$10 -> 166666.67 | V53: =U53*Parametros!$B$11 -> 20000 | W53: =(Q53+R53)*Parametros!$B$12 -> 166666.67 | X53: =Q53*Parametros!$B$13 -> 73012.739 | Y53: =Q53*Parametros!$B$7 -> 148826.92 | Z53: =Q53*Parametros!$B$8 -> 210108.6 | AA53: =Q53*Parametros!$B$9 -> 70036.2 | AB53: =Q53*P53 -> 9139.7241
A54: EMP-053 | B54: Pineda | C54: Miguel | D54: M | E54: 30609 | F54: Soltero | G54: Cundinamarca | H54: SOACHA | I54: CONDUCTOR | J54: 44959 | K54: 46054 | L54: SALUD TOTAL | M54: PORVENIR S.A. | N54: ARL SURA | O54: COLSUBSIDIO | P54: 0.0696 | Q54: 1900000 | R54: =IF(Q54<=Parametros!$B$4,Parametros!$B$3,0) -> 249095 | S54: =Q54*Parametros!$B$5 -> 76000 | T54: =Q54*Parametros!$B$6 -> 76000 | U54: =(Q54+R54)*Parametros!$B$10 -> 179091.25 | V54: =U54*Parametros!$B$11 -> 21490.95 | W54: =(Q54+R54)*Parametros!$B$12 -> 179091.25 | X54: =Q54*Parametros!$B$13 -> 79230 | Y54: =Q54*Parametros!$B$7 -> 161500 | Z54: =Q54*Parametros!$B$8 -> 228000 | AA54: =Q54*Parametros!$B$9 -> 76000 | AB54: =Q54*P54 -> 132240
A55: EMP-054 | B55: Mendoza | C55: Luis | D55: M | E55: 32446 | F55: Soltero | G55: Bogotá D.C | H55: Bogotá | I55: AUXILIAR DE NOMINA | J55: 45352 | L55: FAMISANAR | M55: COLFONDOS | N55: ARL SURA | O55: COLSUBSIDIO | P55: 0.00522 | Q55: 1750905 | R55: =IF(Q55<=Parametros!$B$4,Parametros!$B$3,0) -> 249095 | S55: =Q55*Parametros!$B$5 -> 70036.2 | T55: =Q55*Parametros!$B$6 -> 70036.2 | U55: =(Q55+R55)*Parametros!$B$10 -> 166666.67 | V55: =U55*Parametros!$B$11 -> 20000 | W55: =(Q55+R55)*Parametros!$B$12 -> 166666.67 | X55: =Q55*Parametros!$B$13 -> 73012.739 | Y55: =Q55*Parametros!$B$7 -> 148826.92 | Z55: =Q55*Parametros!$B$8 -> 210108.6 | AA55: =Q55*Parametros!$B$9 -> 70036.2 | AB55: =Q55*P55 -> 9139.7241
A56: EMP-055 | B56: Lopez | C56: David | D56: M | E56: 29479 | F56: Soltero | G56: Bogotá D.C | H56: Bogotá | I56: ANALISTA DE COSTOS | J56: 44380 | L56: COMPENSAR EPS | M56: PORVENIR S.A. | N56: ARL SURA | O56: COLSUBSIDIO | P56: 0.00522 | Q56: 1750905 | R56: =IF(Q56<=Parametros!$B$4,Parametros!$B$3,0) -> 249095 | S56: =Q56*Parametros!$B$5 -> 70036.2 | T56: =Q56*Parametros!$B$6 -> 70036.2 | U56: =(Q56+R56)*Parametros!$B$10 -> 166666.67 | V56: =U56*Parametros!$B$11 -> 20000 | W56: =(Q56+R56)*Parametros!$B$12 -> 166666.67 | X56: =Q56*Parametros!$B$13 -> 73012.739 | Y56: =Q56*Parametros!$B$7 -> 148826.92 | Z56: =Q56*Parametros!$B$8 -> 210108.6 | AA56: =Q56*Parametros!$B$9 -> 70036.2 | AB56: =Q56*P56 -> 9139.7241
A57: EMP-056 | B57: Castro | C57: David | D57: M | E57: 30423 | F57: Soltero | G57: Bogotá D.C | H57: Bogotá | I57: AUXILIAR ADMINISTRATIVO | J57: 45323 | L57: SALUD TOTAL | M57: PORVENIR S.A. | N57: ARL SURA | O57: COLSUBSIDIO | P57: 0.00522 | Q57: 1750905 | R57: =IF(Q57<=Parametros!$B$4,Parametros!$B$3,0) -> 249095 | S57: =Q57*Parametros!$B$5 -> 70036.2 | T57: =Q57*Parametros!$B$6 -> 70036.2 | U57: =(Q57+R57)*Parametros!$B$10 -> 166666.67 | V57: =U57*Parametros!$B$11 -> 20000 | W57: =(Q57+R57)*Parametros!$B$12 -> 166666.67 | X57: =Q57*Parametros!$B$13 -> 73012.739 | Y57: =Q57*Parametros!$B$7 -> 148826.92 | Z57: =Q57*Parametros!$B$8 -> 210108.6 | AA57: =Q57*Parametros!$B$9 -> 70036.2 | AB57: =Q57*P57 -> 9139.7241
A58: EMP-057 | B58: Gonzalez | C58: Ivan | D58: M | E58: 26456 | F58: Soltero | G58: Bogotá D.C | H58: Bogotá | I58: DIRECTOR COMERCIAL | J58: 44623 | L58: COMPENSAR EPS | M58: COLPENSIONES | N58: ARL SURA | O58: COLSUBSIDIO | P58: 0.00522 | Q58: 6500000 | R58: =IF(Q58<=Parametros!$B$4,Parametros!$B$3,0) -> 0 | S58: =Q58*Parametros!$B$5 -> 260000 | T58: =Q58*Parametros!$B$6 -> 260000 | U58: =(Q58+R58)*Parametros!$B$10 -> 541666.67 | V58: =U58*Parametros!$B$11 -> 65000 | W58: =(Q58+R58)*Parametros!$B$12 -> 541666.67 | X58: =Q58*Parametros!$B$13 -> 271050 | Y58: =Q58*Parametros!$B$7 -> 552500 | Z58: =Q58*Parametros!$B$8 -> 780000 | AA58: =Q58*Parametros!$B$9 -> 260000 | AB58: =Q58*P58 -> 33930
A59: EMP-058 | B59: Ortiz | C59: Diego | D59: M | E59: 28481 | F59: Soltero | G59: Bogotá D.C | H59: Bogotá | I59: ASESOR COMERCIAL | J59: 45383 | L59: FAMISANAR | M59: COLPENSIONES | N59: ARL SURA | O59: COLSUBSIDIO | P59: 0.00522 | Q59: 2000000 | R59: =IF(Q59<=Parametros!$B$4,Parametros!$B$3,0) -> 249095 | S59: =Q59*Parametros!$B$5 -> 80000 | T59: =Q59*Parametros!$B$6 -> 80000 | U59: =(Q59+R59)*Parametros!$B$10 -> 187424.58 | V59: =U59*Parametros!$B$11 -> 22490.95 | W59: =(Q59+R59)*Parametros!$B$12 -> 187424.58 | X59: =Q59*Parametros!$B$13 -> 83400 | Y59: =Q59*Parametros!$B$7 -> 170000 | Z59: =Q59*Parametros!$B$8 -> 240000 | AA59: =Q59*Parametros!$B$9 -> 80000 | AB59: =Q59*P59 -> 10440
A60: EMP-059 | B60: Cruz | C60: Catalina | D60: F | E60: 33410 | F60: Soltero | G60: Bogotá D.C | H60: Bogotá | I60: CONDUCTOR | J60: 45536 | L60: FAMISANAR | M60: COLPENSIONES | N60: ARL SURA | O60: COLSUBSIDIO | P60: 0.0696 | Q60: 1900000 | R60: =IF(Q60<=Parametros!$B$4,Parametros!$B$3,0) -> 249095 | S60: =Q60*Parametros!$B$5 -> 76000 | T60: =Q60*Parametros!$B$6 -> 76000 | U60: =(Q60+R60)*Parametros!$B$10 -> 179091.25 | V60: =U60*Parametros!$B$11 -> 21490.95 | W60: =(Q60+R60)*Parametros!$B$12 -> 179091.25 | X60: =Q60*Parametros!$B$13 -> 79230 | Y60: =Q60*Parametros!$B$7 -> 161500 | Z60: =Q60*Parametros!$B$8 -> 228000 | AA60: =Q60*Parametros!$B$9 -> 76000 | AB60: =Q60*P60 -> 132240
A61: EMP-060 | B61: Diaz | C61: Diana | D61: F | E61: 32337 | F61: Soltero | G61: Cundinamarca | H61: SOACHA | I61: AUXILIAR DE BODEGA | J61: 45383 | L61: SALUD TOTAL | M61: PORVENIR S.A. | N61: ARL SURA | O61: COLSUBSIDIO | P61: 0.0435 | Q61: 1750905 | R61: =IF(Q61<=Parametros!$B$4,Parametros!$B$3,0) -> 249095 | S61: =Q61*Parametros!$B$5 -> 70036.2 | T61: =Q61*Parametros!$B$6 -> 70036.2 | U61: =(Q61+R61)*Parametros!$B$10 -> 166666.67 | V61: =U61*Parametros!$B$11 -> 20000 | W61: =(Q61+R61)*Parametros!$B$12 -> 166666.67 | X61: =Q61*Parametros!$B$13 -> 73012.739 | Y61: =Q61*Parametros!$B$7 -> 148826.92 | Z61: =Q61*Parametros!$B$8 -> 210108.6 | AA61: =Q61*Parametros!$B$9 -> 70036.2 | AB61: =Q61*P61 -> 76164.367
A62: EMP-061 | B62: Sanchez | C62: Sofia | D62: F | E62: 25707 | F62: Soltero | G62: Bogotá D.C | H62: Bogotá | I62: CONDUCTOR | J62: 45962 | L62: FAMISANAR | M62: PORVENIR S.A. | N62: ARL SURA | O62: COLSUBSIDIO | P62: 0.0696 | Q62: 1900000 | R62: =IF(Q62<=Parametros!$B$4,Parametros!$B$3,0) -> 249095 | S62: =Q62*Parametros!$B$5 -> 76000 | T62: =Q62*Parametros!$B$6 -> 76000 | U62: =(Q62+R62)*Parametros!$B$10 -> 179091.25 | V62: =U62*Parametros!$B$11 -> 21490.95 | W62: =(Q62+R62)*Parametros!$B$12 -> 179091.25 | X62: =Q62*Parametros!$B$13 -> 79230 | Y62: =Q62*Parametros!$B$7 -> 161500 | Z62: =Q62*Parametros!$B$8 -> 228000 | AA62: =Q62*Parametros!$B$9 -> 76000 | AB62: =Q62*P62 -> 132240
A63: EMP-062 | B63: Medina | C63: Hernan | D63: M | E63: 31416 | F63: Soltero | G63: Bogotá D.C | H63: Bogotá | I63: AUXILIAR ADMINISTRATIVO | J63: 44805 | L63: SURA EPS | M63: PORVENIR S.A. | N63: ARL SURA | O63: COLSUBSIDIO | P63: 0.00522 | Q63: 1750905 | R63: =IF(Q63<=Parametros!$B$4,Parametros!$B$3,0) -> 249095 | S63: =Q63*Parametros!$B$5 -> 70036.2 | T63: =Q63*Parametros!$B$6 -> 70036.2 | U63: =(Q63+R63)*Parametros!$B$10 -> 166666.67 | V63: =U63*Parametros!$B$11 -> 20000 | W63: =(Q63+R63)*Parametros!$B$12 -> 166666.67 | X63: =Q63*Parametros!$B$13 -> 73012.739 | Y63: =Q63*Parametros!$B$7 -> 148826.92 | Z63: =Q63*Parametros!$B$8 -> 210108.6 | AA63: =Q63*Parametros!$B$9 -> 70036.2 | AB63: =Q63*P63 -> 9139.7241
A64: EMP-063 | B64: Bermudez | C64: Andrea | D64: F | E64: 28219 | F64: Soltero | G64: Bogotá D.C | H64: Bogotá | I64: ASESOR COMERCIAL | J64: 46054 | L64: COMPENSAR EPS | M64: COLPENSIONES | N64: ARL SURA | O64: COMPENSAR | P64: 0.00522 | Q64: 2000000 | R64: =IF(Q64<=Parametros!$B$4,Parametros!$B$3,0) -> 249095 | S64: =Q64*Parametros!$B$5 -> 80000 | T64: =Q64*Parametros!$B$6 -> 80000 | U64: =(Q64+R64)*Parametros!$B$10 -> 187424.58 | V64: =U64*Parametros!$B$11 -> 22490.95 | W64: =(Q64+R64)*Parametros!$B$12 -> 187424.58 | X64: =Q64*Parametros!$B$13 -> 83400 | Y64: =Q64*Parametros!$B$7 -> 170000 | Z64: =Q64*Parametros!$B$8 -> 240000 | AA64: =Q64*Parametros!$B$9 -> 80000 | AB64: =Q64*P64 -> 10440
A65: EMP-064 | B65: Lopez | C65: Camila | D65: F | E65: 35172 | F65: Soltero | G65: Cundinamarca | H65: SOACHA | I65: JEFE DE MANTENIMIENTO | J65: 46125 | L65: SANITAS | M65: PORVENIR S.A. | N65: ARL SURA | O65: COLSUBSIDIO | P65: 0.0435 | Q65: 3200000 | R65: =IF(Q65<=Parametros!$B$4,Parametros!$B$3,0) -> 249095 | S65: =Q65*Parametros!$B$5 -> 128000 | T65: =Q65*Parametros!$B$6 -> 128000 | U65: =(Q65+R65)*Parametros!$B$10 -> 287424.58 | V65: =U65*Parametros!$B$11 -> 34490.95 | W65: =(Q65+R65)*Parametros!$B$12 -> 287424.58 | X65: =Q65*Parametros!$B$13 -> 133440 | Y65: =Q65*Parametros!$B$7 -> 272000 | Z65: =Q65*Parametros!$B$8 -> 384000 | AA65: =Q65*Parametros!$B$9 -> 128000 | AB65: =Q65*P65 -> 139200
A66: EMP-065 | B66: Perez | C66: Laura | D66: F | E66: 30722 | F66: Soltero | G66: Bogotá D.C | H66: Bogotá | I66: AUXILIAR ADMINISTRATIVO | J66: 44718 | L66: SALUD TOTAL | M66: PORVENIR S.A. | N66: ARL SURA | O66: COLSUBSIDIO | P66: 0.00522 | Q66: 1750905 | R66: =IF(Q66<=Parametros!$B$4,Parametros!$B$3,0) -> 249095 | S66: =Q66*Parametros!$B$5 -> 70036.2 | T66: =Q66*Parametros!$B$6 -> 70036.2 | U66: =(Q66+R66)*Parametros!$B$10 -> 166666.67 | V66: =U66*Parametros!$B$11 -> 20000 | W66: =(Q66+R66)*Parametros!$B$12 -> 166666.67 | X66: =Q66*Parametros!$B$13 -> 73012.739 | Y66: =Q66*Parametros!$B$7 -> 148826.92 | Z66: =Q66*Parametros!$B$8 -> 210108.6 | AA66: =Q66*Parametros!$B$9 -> 70036.2 | AB66: =Q66*P66 -> 9139.7241
... A69: EMP-068 | B69: Torres | C69: Fabian | D69: M | E69: 31721 | F69: Soltero | G69: Bogotá D.C | H69: Bogotá | I69: AUXILIAR ADMINISTRATIVO | J69: 45891 | L69: SALUD TOTAL | M69: COLPENSIONES | N69: ARL SURA | O69: COMPENSAR | P69: 0.00522 | Q69: 1750905 | R69: =IF(Q69<=Parametros!$B$4,Parametros!$B$3,0) -> 249095 | S69: =Q69*Parametros!$B$5 -> 70036.2 | T69: =Q69*Parametros!$B$6 -> 70036.2 | U69: =(Q69+R69)*Parametros!$B$10 -> 166666.67 | V69: =U69*Parametros!$B$11 -> 20000 | W69: =(Q69+R69)*Parametros!$B$12 -> 166666.67 | X69: =Q69*Parametros!$B$13 -> 73012.739 | Y69: =Q69*Parametros!$B$7 -> 148826.92 | Z69: =Q69*Parametros!$B$8 -> 210108.6 | AA69: =Q69*Parametros!$B$9 -> 70036.2 | AB69: =Q69*P69 -> 9139.7241
A70: EMP-069 | B70: Cadena | C70: Gustavo | D70: M | E70: 30198 | F70: Soltero | G70: Meta | H70: VILLAVICENCIO | I70: AUXILIAR ADMINISTRATIVO | J70: 45763 | K70: 46143 | L70: SANITAS | M70: PORVENIR S.A. | N70: ARL SURA | O70: COLSUBSIDIO | P70: 0.00522 | Q70: 1750905 | R70: =IF(Q70<=Parametros!$B$4,Parametros!$B$3,0) -> 249095 | S70: =Q70*Parametros!$B$5 -> 70036.2 | T70: =Q70*Parametros!$B$6 -> 70036.2 | U70: =(Q70+R70)*Parametros!$B$10 -> 166666.67 | V70: =U70*Parametros!$B$11 -> 20000 | W70: =(Q70+R70)*Parametros!$B$12 -> 166666.67 | X70: =Q70*Parametros!$B$13 -> 73012.739 | Y70: =Q70*Parametros!$B$7 -> 148826.92 | Z70: =Q70*Parametros!$B$8 -> 210108.6 | AA70: =Q70*Parametros!$B$9 -> 70036.2 | AB70: =Q70*P70 -> 9139.7241
A71: EMP-070 | B71: Perez | C71: Sofia | D71: F | E71: 27105 | F71: Soltero | G71: Bogotá D.C | H71: Bogotá | I71: CONTADOR | J71: 46143 | L71: CAPITAL SALUD | M71: COLPENSIONES | N71: ARL SURA | O71: COLSUBSIDIO | P71: 0.00522 | Q71: 4000000 | R71: =IF(Q71<=Parametros!$B$4,Parametros!$B$3,0) -> 0 | S71: =Q71*Parametros!$B$5 -> 160000 | T71: =Q71*Parametros!$B$6 -> 160000 | U71: =(Q71+R71)*Parametros!$B$10 -> 333333.33 | V71: =U71*Parametros!$B$11 -> 40000 | W71: =(Q71+R71)*Parametros!$B$12 -> 333333.33 | X71: =Q71*Parametros!$B$13 -> 166800 | Y71: =Q71*Parametros!$B$7 -> 340000 | Z71: =Q71*Parametros!$B$8 -> 480000 | AA71: =Q71*Parametros!$B$9 -> 160000 | AB71: =Q71*P71 -> 20880
A72: EMP-071 | B72: Guerrero | C72: Julian | D72: M | E72: 29860 | F72: Soltero | G72: Cundinamarca | H72: SOACHA | I72: AUXILIAR DE BODEGA | J72: 45017 | L72: SURA EPS | M72: PROTECCION | N72: ARL SURA | O72: COLSUBSIDIO | P72: 0.0435 | Q72: 1750905 | R72: =IF(Q72<=Parametros!$B$4,Parametros!$B$3,0) -> 249095 | S72: =Q72*Parametros!$B$5 -> 70036.2 | T72: =Q72*Parametros!$B$6 -> 70036.2 | U72: =(Q72+R72)*Parametros!$B$10 -> 166666.67 | V72: =U72*Parametros!$B$11 -> 20000 | W72: =(Q72+R72)*Parametros!$B$12 -> 166666.67 | X72: =Q72*Parametros!$B$13 -> 73012.739 | Y72: =Q72*Parametros!$B$7 -> 148826.92 | Z72: =Q72*Parametros!$B$8 -> 210108.6 | AA72: =Q72*Parametros!$B$9 -> 70036.2 | AB72: =Q72*P72 -> 76164.367
A73: EMP-072 | B73: Aguirre | C73: Wilson | D73: M | E73: 29750 | F73: Soltero | G73: Bogotá D.C | H73: Bogotá | I73: AUXILIAR DE BODEGA | J73: 46174 | L73: SURA EPS | M73: COLPENSIONES | N73: ARL SURA | O73: COLSUBSIDIO | P73: 0.0435 | Q73: 1750905 | R73: =IF(Q73<=Parametros!$B$4,Parametros!$B$3,0) -> 249095 | S73: =Q73*Parametros!$B$5 -> 70036.2 | T73: =Q73*Parametros!$B$6 -> 70036.2 | U73: =(Q73+R73)*Parametros!$B$10 -> 166666.67 | V73: =U73*Parametros!$B$11 -> 20000 | W73: =(Q73+R73)*Parametros!$B$12 -> 166666.67 | X73: =Q73*Parametros!$B$13 -> 73012.739 | Y73: =Q73*Parametros!$B$7 -> 148826.92 | Z73: =Q73*Parametros!$B$8 -> 210108.6 | AA73: =Q73*Parametros!$B$9 -> 70036.2 | AB73: =Q73*P73 -> 76164.367
A74: EMP-073 | B74: Rodriguez | C74: Oscar | D74: M | E74: 27585 | F74: Soltero | G74: Bogotá D.C | H74: Bogotá | I74: CONDUCTOR | J74: 43957 | L74: COMPENSAR EPS | M74: COLPENSIONES | N74: ARL SURA | O74: COMPENSAR | P74: 0.0696 | Q74: 1900000 | R74: =IF(Q74<=Parametros!$B$4,Parametros!$B$3,0) -> 249095 | S74: =Q74*Parametros!$B$5 -> 76000 | T74: =Q74*Parametros!$B$6 -> 76000 | U74: =(Q74+R74)*Parametros!$B$10 -> 179091.25 | V74: =U74*Parametros!$B$11 -> 21490.95 | W74: =(Q74+R74)*Parametros!$B$12 -> 179091.25 | X74: =Q74*Parametros!$B$13 -> 79230 | Y74: =Q74*Parametros!$B$7 -> 161500 | Z74: =Q74*Parametros!$B$8 -> 228000 | AA74: =Q74*Parametros!$B$9 -> 76000 | AB74: =Q74*P74 -> 132240
A75: EMP-074 | B75: Gonzalez | C75: Patricia | D75: F | E75: 31121 | F75: Soltero | G75: Bogotá D.C | H75: Bogotá | I75: COORDINADOR DE INVENTARIOS | J75: 46174 | L75: SURA EPS | M75: COLFONDOS | N75: ARL SURA | O75: COLSUBSIDIO | P75: 0.02436 | Q75: 2800000 | R75: =IF(Q75<=Parametros!$B$4,Parametros!$B$3,0) -> 249095 | S75: =Q75*Parametros!$B$5 -> 112000 | T75: =Q75*Parametros!$B$6 -> 112000 | U75: =(Q75+R75)*Parametros!$B$10 -> 254091.25 | V75: =U75*Parametros!$B$11 -> 30490.95 | W75: =(Q75+R75)*Parametros!$B$12 -> 254091.25 | X75: =Q75*Parametros!$B$13 -> 116760 | Y75: =Q75*Parametros!$B$7 -> 238000 | Z75: =Q75*Parametros!$B$8 -> 336000 | AA75: =Q75*Parametros!$B$9 -> 112000 | AB75: =Q75*P75 -> 68208
A76: EMP-075 | B76: Ortiz | C76: David | D76: M | E76: 33042 | F76: Soltero | G76: Bogotá D.C | H76: Bogotá | I76: CONDUCTOR | J76: 46045 | K76: 46054 | L76: FAMISANAR | M76: PORVENIR S.A. | N76: ARL SURA | O76: COLSUBSIDIO | P76: 0.0696 | Q76: 1900000 | R76: =IF(Q76<=Parametros!$B$4,Parametros!$B$3,0) -> 249095 | S76: =Q76*Parametros!$B$5 -> 76000 | T76: =Q76*Parametros!$B$6 -> 76000 | U76: =(Q76+R76)*Parametros!$B$10 -> 179091.25 | V76: =U76*Parametros!$B$11 -> 21490.95 | W76: =(Q76+R76)*Parametros!$B$12 -> 179091.25 | X76: =Q76*Parametros!$B$13 -> 79230 | Y76: =Q76*Parametros!$B$7 -> 161500 | Z76: =Q76*Parametros!$B$8 -> 228000 | AA76: =Q76*Parametros!$B$9 -> 76000 | AB76: =Q76*P76 -> 132240
A77: EMP-076 | B77: Aguirre | C77: Esteban | D77: M | E77: 30233 | F77: Soltero | G77: Bogotá D.C | H77: Bogotá | I77: CONDUCTOR | J77: 46045 | K77: 46054 | L77: SALUD TOTAL | M77: COLPENSIONES | N77: ARL SURA | O77: COLSUBSIDIO | P77: 0.0696 | Q77: 1900000 | R77: =IF(Q77<=Parametros!$B$4,Parametros!$B$3,0) -> 249095 | S77: =Q77*Parametros!$B$5 -> 76000 | T77: =Q77*Parametros!$B$6 -> 76000 | U77: =(Q77+R77)*Parametros!$B$10 -> 179091.25 | V77: =U77*Parametros!$B$11 -> 21490.95 | W77: =(Q77+R77)*Parametros!$B$12 -> 179091.25 | X77: =Q77*Parametros!$B$13 -> 79230 | Y77: =Q77*Parametros!$B$7 -> 161500 | Z77: =Q77*Parametros!$B$8 -> 228000 | AA77: =Q77*Parametros!$B$9 -> 76000 | AB77: =Q77*P77 -> 132240
A78: EMP-077 | B78: Nunez | C78: Nicolas | D78: M | E78: 35272 | F78: Soltero | G78: Bogotá D.C | H78: Bogotá | I78: AUXILIAR ADMINISTRATIVO | J78: 44409 | L78: NUEVA EPS | M78: COLPENSIONES | N78: ARL SURA | O78: COMPENSAR | P78: 0.00522 | Q78: 1750905 | R78: =IF(Q78<=Parametros!$B$4,Parametros!$B$3,0) -> 249095 | S78: =Q78*Parametros!$B$5 -> 70036.2 | T78: =Q78*Parametros!$B$6 -> 70036.2 | U78: =(Q78+R78)*Parametros!$B$10 -> 166666.67 | V78: =U78*Parametros!$B$11 -> 20000 | W78: =(Q78+R78)*Parametros!$B$12 -> 166666.67 | X78: =Q78*Parametros!$B$13 -> 73012.739 | Y78: =Q78*Parametros!$B$7 -> 148826.92 | Z78: =Q78*Parametros!$B$8 -> 210108.6 | AA78: =Q78*Parametros!$B$9 -> 70036.2 | AB78: =Q78*P78 -> 9139.7241
A79: EMP-078 | B79: Torres | C79: Camilo | D79: M | E79: 25771 | F79: Soltero | G79: Bogotá D.C | H79: Bogotá | I79: AUXILIAR ADMINISTRATIVO | J79: 45033 | L79: FAMISANAR | M79: COLPENSIONES | N79: ARL SURA | O79: COLSUBSIDIO | P79: 0.00522 | Q79: 1750905 | R79: =IF(Q79<=Parametros!$B$4,Parametros!$B$3,0) -> 249095 | S79: =Q79*Parametros!$B$5 -> 70036.2 | T79: =Q79*Parametros!$B$6 -> 70036.2 | U79: =(Q79+R79)*Parametros!$B$10 -> 166666.67 | V79: =U79*Parametros!$B$11 -> 20000 | W79: =(Q79+R79)*Parametros!$B$12 -> 166666.67 | X79: =Q79*Parametros!$B$13 -> 73012.739 | Y79: =Q79*Parametros!$B$7 -> 148826.92 | Z79: =Q79*Parametros!$B$8 -> 210108.6 | AA79: =Q79*Parametros!$B$9 -> 70036.2 | AB79: =Q79*P79 -> 9139.7241
A80: EMP-079 | B80: Suarez | C80: Ricardo | D80: M | E80: 29955 | F80: Soltero | G80: Bogotá D.C | H80: Bogotá | I80: AUXILIAR DE BODEGA | J80: 45092 | L80: COMPENSAR EPS | M80: COLFONDOS | N80: ARL SURA | O80: COLSUBSIDIO | P80: 0.0435 | Q80: 1750905 | R80: =IF(Q80<=Parametros!$B$4,Parametros!$B$3,0) -> 249095 | S80: =Q80*Parametros!$B$5 -> 70036.2 | T80: =Q80*Parametros!$B$6 -> 70036.2 | U80: =(Q80+R80)*Parametros!$B$10 -> 166666.67 | V80: =U80*Parametros!$B$11 -> 20000 | W80: =(Q80+R80)*Parametros!$B$12 -> 166666.67 | X80: =Q80*Parametros!$B$13 -> 73012.739 | Y80: =Q80*Parametros!$B$7 -> 148826.92 | Z80: =Q80*Parametros!$B$8 -> 210108.6 | AA80: =Q80*Parametros!$B$9 -> 70036.2 | AB80: =Q80*P80 -> 76164.367
A81: EMP-080 | B81: Castillo | C81: Natalia | D81: F | E81: 29159 | F81: Soltero | G81: Bogotá D.C | H81: Bogotá | I81: CONDUCTOR | J81: 45694 | L81: SURA EPS | M81: PORVENIR S.A. | N81: ARL SURA | O81: COLSUBSIDIO | P81: 0.0696 | Q81: 1900000 | R81: =IF(Q81<=Parametros!$B$4,Parametros!$B$3,0) -> 249095 | S81: =Q81*Parametros!$B$5 -> 76000 | T81: =Q81*Parametros!$B$6 -> 76000 | U81: =(Q81+R81)*Parametros!$B$10 -> 179091.25 | V81: =U81*Parametros!$B$11 -> 21490.95 | W81: =(Q81+R81)*Parametros!$B$12 -> 179091.25 | X81: =Q81*Parametros!$B$13 -> 79230 | Y81: =Q81*Parametros!$B$7 -> 161500 | Z81: =Q81*Parametros!$B$8 -> 228000 | AA81: =Q81*Parametros!$B$9 -> 76000 | AB81: =Q81*P81 -> 132240
A82: EMP-081 | B82: Bermudez | C82: Vanessa | D82: F | E82: 28939 | F82: Soltero | G82: Bogotá D.C | H82: Bogotá | I82: AUXILIAR DE BODEGA | J82: 43497 | L82: FAMISANAR | M82: PORVENIR S.A. | N82: ARL SURA | O82: COLSUBSIDIO | P82: 0.0435 | Q82: 1750905 | R82: =IF(Q82<=Parametros!$B$4,Parametros!$B$3,0) -> 249095 | S82: =Q82*Parametros!$B$5 -> 70036.2 | T82: =Q82*Parametros!$B$6 -> 70036.2 | U82: =(Q82+R82)*Parametros!$B$10 -> 166666.67 | V82: =U82*Parametros!$B$11 -> 20000 | W82: =(Q82+R82)*Parametros!$B$12 -> 166666.67 | X82: =Q82*Parametros!$B$13 -> 73012.739 | Y82: =Q82*Parametros!$B$7 -> 148826.92 | Z82: =Q82*Parametros!$B$8 -> 210108.6 | AA82: =Q82*Parametros!$B$9 -> 70036.2 | AB82: =Q82*P82 -> 76164.367
A83: EMP-082 | B83: Guerrero | C83: Miguel | D83: M | E83: 33083 | F83: Soltero | G83: Bogotá D.C | H83: Bogotá | I83: AUXILIAR DE BODEGA | J83: 45474 | L83: FAMISANAR | M83: PORVENIR S.A. | N83: ARL SURA | O83: COLSUBSIDIO | P83: 0.0435 | Q83: 1750905 | R83: =IF(Q83<=Parametros!$B$4,Parametros!$B$3,0) -> 249095 | S83: =Q83*Parametros!$B$5 -> 70036.2 | T83: =Q83*Parametros!$B$6 -> 70036.2 | U83: =(Q83+R83)*Parametros!$B$10 -> 166666.67 | V83: =U83*Parametros!$B$11 -> 20000 | W83: =(Q83+R83)*Parametros!$B$12 -> 166666.67 | X83: =Q83*Parametros!$B$13 -> 73012.739 | Y83: =Q83*Parametros!$B$7 -> 148826.92 | Z83: =Q83*Parametros!$B$8 -> 210108.6 | AA83: =Q83*Parametros!$B$9 -> 70036.2 | AB83: =Q83*P83 -> 76164.367
A84: EMP-083 | B84: Pineda | C84: Marcela | D84: F | E84: 26163 | F84: Soltero | G84: Bogotá D.C | H84: Bogotá | I84: ANALISTA DE RUTAS | J84: 45721 | L84: SANITAS | M84: COLPENSIONES | N84: ARL SURA | O84: COLSUBSIDIO | P84: 0.00522 | Q84: 1750905 | R84: =IF(Q84<=Parametros!$B$4,Parametros!$B$3,0) -> 249095 | S84: =Q84*Parametros!$B$5 -> 70036.2 | T84: =Q84*Parametros!$B$6 -> 70036.2 | U84: =(Q84+R84)*Parametros!$B$10 -> 166666.67 | V84: =U84*Parametros!$B$11 -> 20000 | W84: =(Q84+R84)*Parametros!$B$12 -> 166666.67 | X84: =Q84*Parametros!$B$13 -> 73012.739 | Y84: =Q84*Parametros!$B$7 -> 148826.92 | Z84: =Q84*Parametros!$B$8 -> 210108.6 | AA84: =Q84*Parametros!$B$9 -> 70036.2 | AB84: =Q84*P84 -> 9139.7241
A85: EMP-084 | B85: Sanchez | C85: Wilson | D85: M | E85: 31616 | F85: Soltero | G85: Bogotá D.C | H85: Bogotá | I85: CONDUCTOR | J85: 45001 | K85: 46143 | L85: COMPENSAR EPS | M85: COLPENSIONES | N85: ARL SURA | O85: COLSUBSIDIO | P85: 0.0696 | Q85: 1900000 | R85: =IF(Q85<=Parametros!$B$4,Parametros!$B$3,0) -> 249095 | S85: =Q85*Parametros!$B$5 -> 76000 | T85: =Q85*Parametros!$B$6 -> 76000 | U85: =(Q85+R85)*Parametros!$B$10 -> 179091.25 | V85: =U85*Parametros!$B$11 -> 21490.95 | W85: =(Q85+R85)*Parametros!$B$12 -> 179091.25 | X85: =Q85*Parametros!$B$13 -> 79230 | Y85: =Q85*Parametros!$B$7 -> 161500 | Z85: =Q85*Parametros!$B$8 -> 228000 | AA85: =Q85*Parametros!$B$9 -> 76000 | AB85: =Q85*P85 -> 132240
A86: EMP-085 | B86: Sanchez | C86: Natalia | D86: F | E86: 26588 | F86: Soltero | G86: Bogotá D.C | H86: Bogotá | I86: DIRECTOR LOGISTICO | J86: 45440 | L86: SANITAS | M86: COLFONDOS | N86: ARL SURA | O86: COLSUBSIDIO | P86: 0.00522 | Q86: 6800000 | R86: =IF(Q86<=Parametros!$B$4,Parametros!$B$3,0) -> 0 | S86: =Q86*Parametros!$B$5 -> 272000 | T86: =Q86*Parametros!$B$6 -> 272000 | U86: =(Q86+R86)*Parametros!$B$10 -> 566666.67 | V86: =U86*Parametros!$B$11 -> 68000 | W86: =(Q86+R86)*Parametros!$B$12 -> 566666.67 | X86: =Q86*Parametros!$B$13 -> 283560 | Y86: =Q86*Parametros!$B$7 -> 578000 | Z86: =Q86*Parametros!$B$8 -> 816000 | AA86: =Q86*Parametros!$B$9 -> 272000 | AB86: =Q86*P86 -> 35496
A87: EMP-086 | B87: Cardenas | C87: Juan | D87: M | E87: 36171 | F87: Soltero | G87: Bogotá D.C | H87: Bogotá | I87: ASESOR COMERCIAL | J87: 45440 | L87: SANITAS | M87: PROTECCION | N87: ARL SURA | O87: COMPENSAR | P87: 0.00522 | Q87: 2000000 | R87: =IF(Q87<=Parametros!$B$4,Parametros!$B$3,0) -> 249095 | S87: =Q87*Parametros!$B$5 -> 80000 | T87: =Q87*Parametros!$B$6 -> 80000 | U87: =(Q87+R87)*Parametros!$B$10 -> 187424.58 | V87: =U87*Parametros!$B$11 -> 22490.95 | W87: =(Q87+R87)*Parametros!$B$12 -> 187424.58 | X87: =Q87*Parametros!$B$13 -> 83400 | Y87: =Q87*Parametros!$B$7 -> 170000 | Z87: =Q87*Parametros!$B$8 -> 240000 | AA87: =Q87*Parametros!$B$9 -> 80000 | AB87: =Q87*P87 -> 10440
A88: EMP-087 | B88: Ospina | C88: David | D88: M | E88: 29584 | F88: Soltero | G88: Bogotá D.C | H88: Bogotá | I88: CONDUCTOR | J88: 45689 | L88: FAMISANAR | M88: COLPENSIONES | N88: ARL SURA | O88: COLSUBSIDIO | P88: 0.0696 | Q88: 1900000 | R88: =IF(Q88<=Parametros!$B$4,Parametros!$B$3,0) -> 249095 | S88: =Q88*Parametros!$B$5 -> 76000 | T88: =Q88*Parametros!$B$6 -> 76000 | U88: =(Q88+R88)*Parametros!$B$10 -> 179091.25 | V88: =U88*Parametros!$B$11 -> 21490.95 | W88: =(Q88+R88)*Parametros!$B$12 -> 179091.25 | X88: =Q88*Parametros!$B$13 -> 79230 | Y88: =Q88*Parametros!$B$7 -> 161500 | Z88: =Q88*Parametros!$B$8 -> 228000 | AA88: =Q88*Parametros!$B$9 -> 76000 | AB88: =Q88*P88 -> 132240
A89: EMP-088 | B89: Pineda | C89: Claudia | D89: F | E89: 27307 | F89: Soltero | G89: Bogotá D.C | H89: Bogotá | I89: TESORERO | J89: 43831 | L89: FAMISANAR | M89: PORVENIR S.A. | N89: ARL SURA | O89: COLSUBSIDIO | P89: 0.00522 | Q89: 3800000 | R89: =IF(Q89<=Parametros!$B$4,Parametros!$B$3,0) -> 0 | S89: =Q89*Parametros!$B$5 -> 152000 | T89: =Q89*Parametros!$B$6 -> 152000 | U89: =(Q89+R89)*Parametros!$B$10 -> 316666.67 | V89: =U89*Parametros!$B$11 -> 38000 | W89: =(Q89+R89)*Parametros!$B$12 -> 316666.67 | X89: =Q89*Parametros!$B$13 -> 158460 | Y89: =Q89*Parametros!$B$7 -> 323000 | Z89: =Q89*Parametros!$B$8 -> 456000 | AA89: =Q89*Parametros!$B$9 -> 152000 | AB89: =Q89*P89 -> 19836
A90: EMP-089 | B90: Pineda | C90: Mauricio | D90: M | E90: 29538 | F90: Soltero | G90: Bogotá D.C | H90: Bogotá | I90: ASESOR COMERCIAL | J90: 46196 | L90: SANITAS | M90: PROTECCION | N90: ARL SURA | O90: COLSUBSIDIO | P90: 0.00522 | Q90: 2000000 | R90: =IF(Q90<=Parametros!$B$4,Parametros!$B$3,0) -> 249095 | S90: =Q90*Parametros!$B$5 -> 80000 | T90: =Q90*Parametros!$B$6 -> 80000 | U90: =(Q90+R90)*Parametros!$B$10 -> 187424.58 | V90: =U90*Parametros!$B$11 -> 22490.95 | W90: =(Q90+R90)*Parametros!$B$12 -> 187424.58 | X90: =Q90*Parametros!$B$13 -> 83400 | Y90: =Q90*Parametros!$B$7 -> 170000 | Z90: =Q90*Parametros!$B$8 -> 240000 | AA90: =Q90*Parametros!$B$9 -> 80000 | AB90: =Q90*P90 -> 10440
A91: EMP-090 | B91: Romero | C91: Adriana | D91: F | E91: 25955 | F91: Soltero | G91: Bogotá D.C | H91: Bogotá | I91: CONDUCTOR | J91: 46082 | K91: 46082 | L91: COMPENSAR EPS | M91: PROTECCION | N91: ARL SURA | O91: COLSUBSIDIO | P91: 0.0696 | Q91: 1900000 | R91: =IF(Q91<=Parametros!$B$4,Parametros!$B$3,0) -> 249095 | S91: =Q91*Parametros!$B$5 -> 76000 | T91: =Q91*Parametros!$B$6 -> 76000 | U91: =(Q91+R91)*Parametros!$B$10 -> 179091.25 | V91: =U91*Parametros!$B$11 -> 21490.95 | W91: =(Q91+R91)*Parametros!$B$12 -> 179091.25 | X91: =Q91*Parametros!$B$13 -> 79230 | Y91: =Q91*Parametros!$B$7 -> 161500 | Z91: =Q91*Parametros!$B$8 -> 228000 | AA91: =Q91*Parametros!$B$9 -> 76000 | AB91: =Q91*P91 -> 132240
A92: EMP-091 | B92: Hernandez | C92: Isabel | D92: F | E92: 29803 | F92: Soltero | G92: Bogotá D.C | H92: Bogotá | I92: AUXILIAR ADMINISTRATIVO | J92: 45727 | L92: FAMISANAR | M92: PROTECCION | N92: ARL SURA | O92: COLSUBSIDIO | P92: 0.00522 | Q92: 1750905 | R92: =IF(Q92<=Parametros!$B$4,Parametros!$B$3,0) -> 249095 | S92: =Q92*Parametros!$B$5 -> 70036.2 | T92: =Q92*Parametros!$B$6 -> 70036.2 | U92: =(Q92+R92)*Parametros!$B$10 -> 166666.67 | V92: =U92*Parametros!$B$11 -> 20000 | W92: =(Q92+R92)*Parametros!$B$12 -> 166666.67 | X92: =Q92*Parametros!$B$13 -> 73012.739 | Y92: =Q92*Parametros!$B$7 -> 148826.92 | Z92: =Q92*Parametros!$B$8 -> 210108.6 | AA92: =Q92*Parametros!$B$9 -> 70036.2 | AB92: =Q92*P92 -> 9139.7241
A93: EMP-092 | B93: Torres | C93: Oscar | D93: M | E93: 24295 | F93: Soltero | G93: Bogotá D.C | H93: Bogotá | I93: CONDUCTOR | J93: 45895 | L93: COMPENSAR EPS | M93: COLPENSIONES | N93: ARL SURA | O93: COLSUBSIDIO | P93: 0.0696 | Q93: 1900000 | R93: =IF(Q93<=Parametros!$B$4,Parametros!$B$3,0) -> 249095 | S93: =Q93*Parametros!$B$5 -> 76000 | T93: =Q93*Parametros!$B$6 -> 76000 | U93: =(Q93+R93)*Parametros!$B$10 -> 179091.25 | V93: =U93*Parametros!$B$11 -> 21490.95 | W93: =(Q93+R93)*Parametros!$B$12 -> 179091.25 | X93: =Q93*Parametros!$B$13 -> 79230 | Y93: =Q93*Parametros!$B$7 -> 161500 | Z93: =Q93*Parametros!$B$8 -> 228000 | AA93: =Q93*Parametros!$B$9 -> 76000 | AB93: =Q93*P93 -> 132240
A94: EMP-093 | B94: Perez | C94: Ximena | D94: F | E94: 29463 | F94: Soltero | G94: Bogotá D.C | H94: Bogotá | I94: AUXILIAR DE BODEGA | J94: 43741 | L94: SANITAS | M94: COLFONDOS | N94: ARL SURA | O94: COLSUBSIDIO | P94: 0.0435 | Q94: 1750905 | R94: =IF(Q94<=Parametros!$B$4,Parametros!$B$3,0) -> 249095 | S94: =Q94*Parametros!$B$5 -> 70036.2 | T94: =Q94*Parametros!$B$6 -> 70036.2 | U94: =(Q94+R94)*Parametros!$B$10 -> 166666.67 | V94: =U94*Parametros!$B$11 -> 20000 | W94: =(Q94+R94)*Parametros!$B$12 -> 166666.67 | X94: =Q94*Parametros!$B$13 -> 73012.739 | Y94: =Q94*Parametros!$B$7 -> 148826.92 | Z94: =Q94*Parametros!$B$8 -> 210108.6 | AA94: =Q94*Parametros!$B$9 -> 70036.2 | AB94: =Q94*P94 -> 76164.367
A95: EMP-094 | B95: Medina | C95: Nicolas | D95: M | E95: 33246 | F95: Soltero | G95: Cundinamarca | H95: SOACHA | I95: AUXILIAR ADMINISTRATIVO | J95: 45397 | L95: FAMISANAR | M95: PROTECCION | N95: ARL SURA | O95: COLSUBSIDIO | P95: 0.00522 | Q95: 1750905 | R95: =IF(Q95<=Parametros!$B$4,Parametros!$B$3,0) -> 249095 | S95: =Q95*Parametros!$B$5 -> 70036.2 | T95: =Q95*Parametros!$B$6 -> 70036.2 | U95: =(Q95+R95)*Parametros!$B$10 -> 166666.67 | V95: =U95*Parametros!$B$11 -> 20000 | W95: =(Q95+R95)*Parametros!$B$12 -> 166666.67 | X95: =Q95*Parametros!$B$13 -> 73012.739 | Y95: =Q95*Parametros!$B$7 -> 148826.92 | Z95: =Q95*Parametros!$B$8 -> 210108.6 | AA95: =Q95*Parametros!$B$9 -> 70036.2 | AB95: =Q95*P95 -> 9139.7241
A96: EMP-095 | B96: Suarez | C96: Ricardo | D96: M | E96: 34260 | F96: Soltero | G96: Bogotá D.C | H96: Bogotá | I96: CONDUCTOR | J96: 46071 | L96: SANITAS | M96: PORVENIR S.A. | N96: ARL SURA | O96: COLSUBSIDIO | P96: 0.0696 | Q96: 1900000 | R96: =IF(Q96<=Parametros!$B$4,Parametros!$B$3,0) -> 249095 | S96: =Q96*Parametros!$B$5 -> 76000 | T96: =Q96*Parametros!$B$6 -> 76000 | U96: =(Q96+R96)*Parametros!$B$10 -> 179091.25 | V96: =U96*Parametros!$B$11 -> 21490.95 | W96: =(Q96+R96)*Parametros!$B$12 -> 179091.25 | X96: =Q96*Parametros!$B$13 -> 79230 | Y96: =Q96*Parametros!$B$7 -> 161500 | Z96: =Q96*Parametros!$B$8 -> 228000 | AA96: =Q96*Parametros!$B$9 -> 76000 | AB96: =Q96*P96 -> 132240
A97: EMP-096 | B97: Pineda | C97: Cristian | D97: M | E97: 32559 | F97: Soltero | G97: Bogotá D.C | H97: Bogotá | I97: AUXILIAR DE BODEGA | J97: 44440 | L97: SANITAS | M97: PORVENIR S.A. | N97: ARL SURA | O97: COLSUBSIDIO | P97: 0.0435 | Q97: 1750905 | R97: =IF(Q97<=Parametros!$B$4,Parametros!$B$3,0) -> 249095 | S97: =Q97*Parametros!$B$5 -> 70036.2 | T97: =Q97*Parametros!$B$6 -> 70036.2 | U97: =(Q97+R97)*Parametros!$B$10 -> 166666.67 | V97: =U97*Parametros!$B$11 -> 20000 | W97: =(Q97+R97)*Parametros!$B$12 -> 166666.67 | X97: =Q97*Parametros!$B$13 -> 73012.739 | Y97: =Q97*Parametros!$B$7 -> 148826.92 | Z97: =Q97*Parametros!$B$8 -> 210108.6 | AA97: =Q97*Parametros!$B$9 -> 70036.2 | AB97: =Q97*P97 -> 76164.367
A98: EMP-097 | B98: Diaz | C98: Andrea | D98: F | E98: 25554 | F98: Soltero | G98: Bogotá D.C | H98: Bogotá | I98: AUXILIAR CONTABLE | J98: 43476 | L98: SANITAS | M98: COLFONDOS | N98: ARL SURA | O98: COLSUBSIDIO | P98: 0.00522 | Q98: 1750905 | R98: =IF(Q98<=Parametros!$B$4,Parametros!$B$3,0) -> 249095 | S98: =Q98*Parametros!$B$5 -> 70036.2 | T98: =Q98*Parametros!$B$6 -> 70036.2 | U98: =(Q98+R98)*Parametros!$B$10 -> 166666.67 | V98: =U98*Parametros!$B$11 -> 20000 | W98: =(Q98+R98)*Parametros!$B$12 -> 166666.67 | X98: =Q98*Parametros!$B$13 -> 73012.739 | Y98: =Q98*Parametros!$B$7 -> 148826.92 | Z98: =Q98*Parametros!$B$8 -> 210108.6 | AA98: =Q98*Parametros!$B$9 -> 70036.2 | AB98: =Q98*P98 -> 9139.7241
A99: EMP-098 | B99: Salazar | C99: Luis | D99: M | E99: 30477 | F99: Soltero | G99: Bogotá D.C | H99: Bogotá | I99: AUXILIAR DE BODEGA | J99: 45433 | L99: SANITAS | M99: COLFONDOS | N99: ARL SURA | O99: COLSUBSIDIO | P99: 0.0435 | Q99: 1750905 | R99: =IF(Q99<=Parametros!$B$4,Parametros!$B$3,0) -> 249095 | S99: =Q99*Parametros!$B$5 -> 70036.2 | T99: =Q99*Parametros!$B$6 -> 70036.2 | U99: =(Q99+R99)*Parametros!$B$10 -> 166666.67 | V99: =U99*Parametros!$B$11 -> 20000 | W99: =(Q99+R99)*Parametros!$B$12 -> 166666.67 | X99: =Q99*Parametros!$B$13 -> 73012.739 | Y99: =Q99*Parametros!$B$7 -> 148826.92 | Z99: =Q99*Parametros!$B$8 -> 210108.6 | AA99: =Q99*Parametros!$B$9 -> 70036.2 | AB99: =Q99*P99 -> 76164.367
A100: EMP-099 | B100: Rodriguez | C100: Mauricio | D100: M | E100: 31271 | F100: Soltero | G100: Bogotá D.C | H100: Bogotá | I100: AUXILIAR DE BODEGA | J100: 46062 | L100: SANITAS | M100: PORVENIR S.A. | N100: ARL SURA | O100: COMPENSAR | P100: 0.0435 | Q100: 1750905 | R100: =IF(Q100<=Parametros!$B$4,Parametros!$B$3,0) -> 249095 | S100: =Q100*Parametros!$B$5 -> 70036.2 | T100: =Q100*Parametros!$B$6 -> 70036.2 | U100: =(Q100+R100)*Parametros!$B$10 -> 166666.67 | V100: =U100*Parametros!$B$11 -> 20000 | W100: =(Q100+R100)*Parametros!$B$12 -> 166666.67 | X100: =Q100*Parametros!$B$13 -> 73012.739 | Y100: =Q100*Parametros!$B$7 -> 148826.92 | Z100: =Q100*Parametros!$B$8 -> 210108.6 | AA100: =Q100*Parametros!$B$9 -> 70036.2 | AB100: =Q100*P100 -> 76164.367
A101: EMP-100 | B101: Ortiz | C101: Julian | D101: M | E101: 27455 | F101: Soltero | G101: Bogotá D.C | H101: Bogotá | I101: CONDUCTOR | J101: 45973 | L101: COMPENSAR EPS | M101: PORVENIR S.A. | N101: ARL SURA | O101: COLSUBSIDIO | P101: 0.0696 | Q101: 1900000 | R101: =IF(Q101<=Parametros!$B$4,Parametros!$B$3,0) -> 249095 | S101: =Q101*Parametros!$B$5 -> 76000 | T101: =Q101*Parametros!$B$6 -> 76000 | U101: =(Q101+R101)*Parametros!$B$10 -> 179091.25 | V101: =U101*Parametros!$B$11 -> 21490.95 | W101: =(Q101+R101)*Parametros!$B$12 -> 179091.25 | X101: =Q101*Parametros!$B$13 -> 79230 | Y101: =Q101*Parametros!$B$7 -> 161500 | Z101: =Q101*Parametros!$B$8 -> 228000 | AA101: =Q101*Parametros!$B$9 -> 76000 | AB101: =Q101*P101 -> 132240
A102: EMP-101 | B102: Salazar | C102: Miguel | D102: M | E102: 36921 | F102: Soltero | G102: Bogotá D.C | H102: Bogotá | I102: AUXILIAR DE BODEGA | J102: 46148 | L102: FAMISANAR | M102: PROTECCION | N102: ARL SURA | O102: COLSUBSIDIO | P102: 0.0435 | Q102: 1750905 | R102: =IF(Q102<=Parametros!$B$4,Parametros!$B$3,0) -> 249095 | S102: =Q102*Parametros!$B$5 -> 70036.2 | T102: =Q102*Parametros!$B$6 -> 70036.2 | U102: =(Q102+R102)*Parametros!$B$10 -> 166666.67 | V102: =U102*Parametros!$B$11 -> 20000 | W102: =(Q102+R102)*Parametros!$B$12 -> 166666.67 | X102: =Q102*Parametros!$B$13 -> 73012.739 | Y102: =Q102*Parametros!$B$7 -> 148826.92 | Z102: =Q102*Parametros!$B$8 -> 210108.6 | AA102: =Q102*Parametros!$B$9 -> 70036.2 | AB102: =Q102*P102 -> 76164.367
A103: EMP-102 | B103: Guerrero | C103: Tatiana | D103: F | E103: 34454 | F103: Soltero | G103: Cundinamarca | H103: SOACHA | I103: SUPERVISOR DE BODEGA | J103: 46091 | K103: 46143 | L103: SANITAS | M103: COLFONDOS | N103: ARL SURA | O103: COLSUBSIDIO | P103: 0.0435 | Q103: 2600000 | R103: =IF(Q103<=Parametros!$B$4,Parametros!$B$3,0) -> 249095 | S103: =Q103*Parametros!$B$5 -> 104000 | T103: =Q103*Parametros!$B$6 -> 104000 | U103: =(Q103+R103)*Parametros!$B$10 -> 237424.58 | V103: =U103*Parametros!$B$11 -> 28490.95 | W103: =(Q103+R103)*Parametros!$B$12 -> 237424.58 | X103: =Q103*Parametros!$B$13 -> 108420 | Y103: =Q103*Parametros!$B$7 -> 221000 | Z103: =Q103*Parametros!$B$8 -> 312000 | AA103: =Q103*Parametros!$B$9 -> 104000 | AB103: =Q103*P103 -> 113100
A104: EMP-103 | B104: Torres | C104: Oscar | D104: M | E104: 26143 | F104: Soltero | G104: Bogotá D.C | H104: Bogotá | I104: SUPERVISOR DE BODEGA | J104: 45220 | L104: FAMISANAR | M104: COLPENSIONES | N104: ARL SURA | O104: COLSUBSIDIO | P104: 0.0435 | Q104: 2600000 | R104: =IF(Q104<=Parametros!$B$4,Parametros!$B$3,0) -> 249095 | S104: =Q104*Parametros!$B$5 -> 104000 | T104: =Q104*Parametros!$B$6 -> 104000 | U104: =(Q104+R104)*Parametros!$B$10 -> 237424.58 | V104: =U104*Parametros!$B$11 -> 28490.95 | W104: =(Q104+R104)*Parametros!$B$12 -> 237424.58 | X104: =Q104*Parametros!$B$13 -> 108420 | Y104: =Q104*Parametros!$B$7 -> 221000 | Z104: =Q104*Parametros!$B$8 -> 312000 | AA104: =Q104*Parametros!$B$9 -> 104000 | AB104: =Q104*P104 -> 113100
A105: EMP-104 | B105: Cadena | C105: Jorge | D105: M | E105: 30472 | F105: Soltero | G105: Bogotá D.C | H105: Bogotá | I105: DIRECTOR RECURSOS HUMANOS | J105: 44628 | L105: FAMISANAR | M105: PROTECCION | N105: ARL SURA | O105: COLSUBSIDIO | P105: 0.00522 | Q105: 6200000 | R105: =IF(Q105<=Parametros!$B$4,Parametros!$B$3,0) -> 0 | S105: =Q105*Parametros!$B$5 -> 248000 | T105: =Q105*Parametros!$B$6 -> 248000 | U105: =(Q105+R105)*Parametros!$B$10 -> 516666.67 | V105: =U105*Parametros!$B$11 -> 62000 | W105: =(Q105+R105)*Parametros!$B$12 -> 516666.67 | X105: =Q105*Parametros!$B$13 -> 258540 | Y105: =Q105*Parametros!$B$7 -> 527000 | Z105: =Q105*Parametros!$B$8 -> 744000 | AA105: =Q105*Parametros!$B$9 -> 248000 | AB105: =Q105*P105 -> 32364
A106: EMP-105 | B106: Rodriguez | C106: Esteban | D106: M | E106: 35743 | F106: Soltero | G106: Cundinamarca | H106: SOACHA | I106: ANALISTA DE INVENTARIOS | J106: 45936 | L106: SALUD TOTAL | M106: PORVENIR S.A. | N106: ARL SURA | O106: COLSUBSIDIO | P106: 0.00522 | Q106: 1750905 | R106: =IF(Q106<=Parametros!$B$4,Parametros!$B$3,0) -> 249095 | S106: =Q106*Parametros!$B$5 -> 70036.2 | T106: =Q106*Parametros!$B$6 -> 70036.2 | U106: =(Q106+R106)*Parametros!$B$10 -> 166666.67 | V106: =U106*Parametros!$B$11 -> 20000 | W106: =(Q106+R106)*Parametros!$B$12 -> 166666.67 | X106: =Q106*Parametros!$B$13 -> 73012.739 | Y106: =Q106*Parametros!$B$7 -> 148826.92 | Z106: =Q106*Parametros!$B$8 -> 210108.6 | AA106: =Q106*Parametros!$B$9 -> 70036.2 | AB106: =Q106*P106 -> 9139.7241
A107: EMP-106 | B107: Salazar | C107: Adriana | D107: F | E107: 28251 | F107: Soltero | G107: Bogotá D.C | H107: Bogotá | I107: CAJERO | J107: 44896 | L107: FAMISANAR | M107: PROTECCION | N107: ARL SURA | O107: COLSUBSIDIO | P107: 0.00522 | Q107: 1800000 | R107: =IF(Q107<=Parametros!$B$4,Parametros!$B$3,0) -> 249095 | S107: =Q107*Parametros!$B$5 -> 72000 | T107: =Q107*Parametros!$B$6 -> 72000 | U107: =(Q107+R107)*Parametros!$B$10 -> 170757.92 | V107: =U107*Parametros!$B$11 -> 20490.95 | W107: =(Q107+R107)*Parametros!$B$12 -> 170757.92 | X107: =Q107*Parametros!$B$13 -> 75060 | Y107: =Q107*Parametros!$B$7 -> 153000 | Z107: =Q107*Parametros!$B$8 -> 216000 | AA107: =Q107*Parametros!$B$9 -> 72000 | AB107: =Q107*P107 -> 9396
A108: EMP-107 | B108: Romero | C108: Julian | D108: M | E108: 28769 | F108: Soltero | G108: Bogotá D.C | H108: Bogotá | I108: CONDUCTOR | J108: 43563 | L108: COMPENSAR EPS | M108: PORVENIR S.A. | N108: ARL SURA | O108: COLSUBSIDIO | P108: 0.0696 | Q108: 1900000 | R108: =IF(Q108<=Parametros!$B$4,Parametros!$B$3,0) -> 249095 | S108: =Q108*Parametros!$B$5 -> 76000 | T108: =Q108*Parametros!$B$6 -> 76000 | U108: =(Q108+R108)*Parametros!$B$10 -> 179091.25 | V108: =U108*Parametros!$B$11 -> 21490.95 | W108: =(Q108+R108)*Parametros!$B$12 -> 179091.25 | X108: =Q108*Parametros!$B$13 -> 79230 | Y108: =Q108*Parametros!$B$7 -> 161500 | Z108: =Q108*Parametros!$B$8 -> 228000 | AA108: =Q108*Parametros!$B$9 -> 76000 | AB108: =Q108*P108 -> 132240
A109: EMP-108 | B109: Hernandez | C109: Andres | D109: M | E109: 31067 | F109: Soltero | G109: Bogotá D.C | H109: Bogotá | I109: ANALISTA DE RUTAS | J109: 46098 | L109: SALUD TOTAL | M109: PORVENIR S.A. | N109: ARL SURA | O109: COLSUBSIDIO | P109: 0.00522 | Q109: 1750905 | R109: =IF(Q109<=Parametros!$B$4,Parametros!$B$3,0) -> 249095 | S109: =Q109*Parametros!$B$5 -> 70036.2 | T109: =Q109*Parametros!$B$6 -> 70036.2 | U109: =(Q109+R109)*Parametros!$B$10 -> 166666.67 | V109: =U109*Parametros!$B$11 -> 20000 | W109: =(Q109+R109)*Parametros!$B$12 -> 166666.67 | X109: =Q109*Parametros!$B$13 -> 73012.739 | Y109: =Q109*Parametros!$B$7 -> 148826.92 | Z109: =Q109*Parametros!$B$8 -> 210108.6 | AA109: =Q109*Parametros!$B$9 -> 70036.2 | AB109: =Q109*P109 -> 9139.7241
A110: EMP-109 | B110: Suarez | C110: Yolanda | D110: F | E110: 25408 | F110: Soltero | G110: Bogotá D.C | H110: Bogotá | I110: AUXILIAR DE BODEGA | J110: 45670 | L110: SURA EPS | M110: COLPENSIONES | N110: ARL SURA | O110: COLSUBSIDIO | P110: 0.0435 | Q110: 1750905 | R110: =IF(Q110<=Parametros!$B$4,Parametros!$B$3,0) -> 249095 | S110: =Q110*Parametros!$B$5 -> 70036.2 | T110: =Q110*Parametros!$B$6 -> 70036.2 | U110: =(Q110+R110)*Parametros!$B$10 -> 166666.67 | V110: =U110*Parametros!$B$11 -> 20000 | W110: =(Q110+R110)*Parametros!$B$12 -> 166666.67 | X110: =Q110*Parametros!$B$13 -> 73012.739 | Y110: =Q110*Parametros!$B$7 -> 148826.92 | Z110: =Q110*Parametros!$B$8 -> 210108.6 | AA110: =Q110*Parametros!$B$9 -> 70036.2 | AB110: =Q110*P110 -> 76164.367
A111: EMP-110 | B111: Salazar | C111: Andrea | D111: F | E111: 29859 | F111: Soltero | G111: Bogotá D.C | H111: Bogotá | I111: COORDINADOR DE FLOTA | J111: 43606 | L111: SANITAS | M111: PROTECCION | N111: ARL SURA | O111: COLSUBSIDIO | P111: 0.02436 | Q111: 3000000 | R111: =IF(Q111<=Parametros!$B$4,Parametros!$B$3,0) -> 249095 | S111: =Q111*Parametros!$B$5 -> 120000 | T111: =Q111*Parametros!$B$6 -> 120000 | U111: =(Q111+R111)*Parametros!$B$10 -> 270757.92 | V111: =U111*Parametros!$B$11 -> 32490.95 | W111: =(Q111+R111)*Parametros!$B$12 -> 270757.92 | X111: =Q111*Parametros!$B$13 -> 125100 | Y111: =Q111*Parametros!$B$7 -> 255000 | Z111: =Q111*Parametros!$B$8 -> 360000 | AA111: =Q111*Parametros!$B$9 -> 120000 | AB111: =Q111*P111 -> 73080
A112: EMP-111 | B112: Guerrero | C112: Wilson | D112: M | E112: 33268 | F112: Soltero | G112: Bogotá D.C | H112: Bogotá | I112: CONDUCTOR | J112: 43617 | L112: FAMISANAR | M112: PORVENIR S.A. | N112: ARL SURA | O112: COLSUBSIDIO | P112: 0.0696 | Q112: 1900000 | R112: =IF(Q112<=Parametros!$B$4,Parametros!$B$3,0) -> 249095 | S112: =Q112*Parametros!$B$5 -> 76000 | T112: =Q112*Parametros!$B$6 -> 76000 | U112: =(Q112+R112)*Parametros!$B$10 -> 179091.25 | V112: =U112*Parametros!$B$11 -> 21490.95 | W112: =(Q112+R112)*Parametros!$B$12 -> 179091.25 | X112: =Q112*Parametros!$B$13 -> 79230 | Y112: =Q112*Parametros!$B$7 -> 161500 | Z112: =Q112*Parametros!$B$8 -> 228000 | AA112: =Q112*Parametros!$B$9 -> 76000 | AB112: =Q112*P112 -> 132240
A113: EMP-112 | B113: Diaz | C113: Alejandro | D113: M | E113: 28571 | F113: Soltero | G113: Bogotá D.C | H113: Bogotá | I113: CONDUCTOR | J113: 46028 | L113: SURA EPS | M113: PROTECCION | N113: ARL SURA | O113: COLSUBSIDIO | P113: 0.0696 | Q113: 1900000 | R113: =IF(Q113<=Parametros!$B$4,Parametros!$B$3,0) -> 249095 | S113: =Q113*Parametros!$B$5 -> 76000 | T113: =Q113*Parametros!$B$6 -> 76000 | U113: =(Q113+R113)*Parametros!$B$10 -> 179091.25 | V113: =U113*Parametros!$B$11 -> 21490.95 | W113: =(Q113+R113)*Parametros!$B$12 -> 179091.25 | X113: =Q113*Parametros!$B$13 -> 79230 | Y113: =Q113*Parametros!$B$7 -> 161500 | Z113: =Q113*Parametros!$B$8 -> 228000 | AA113: =Q113*Parametros!$B$9 -> 76000 | AB113: =Q113*P113 -> 132240
A114: EMP-113 | B114: Castillo | C114: David | D114: M | E114: 29419 | F114: Soltero | G114: Bogotá D.C | H114: Bogotá | I114: MECANICO | J114: 45901 | L114: SANITAS | M114: PROTECCION | N114: ARL SURA | O114: COLSUBSIDIO | P114: 0.0696 | Q114: 2300000 | R114: =IF(Q114<=Parametros!$B$4,Parametros!$B$3,0) -> 249095 | S114: =Q114*Parametros!$B$5 -> 92000 | T114: =Q114*Parametros!$B$6 -> 92000 | U114: =(Q114+R114)*Parametros!$B$10 -> 212424.58 | V114: =U114*Parametros!$B$11 -> 25490.95 | W114: =(Q114+R114)*Parametros!$B$12 -> 212424.58 | X114: =Q114*Parametros!$B$13 -> 95910 | Y114: =Q114*Parametros!$B$7 -> 195500 | Z114: =Q114*Parametros!$B$8 -> 276000 | AA114: =Q114*Parametros!$B$9 -> 92000 | AB114: =Q114*P114 -> 160080
A115: EMP-114 | B115: Rojas | C115: Anderson | D115: M | E115: 29836 | F115: Soltero | G115: Bogotá D.C | H115: Bogotá | I115: COORDINADOR DE FLOTA | J115: 45944 | K115: 46082 | L115: COMPENSAR EPS | M115: COLPENSIONES | N115: ARL SURA | O115: COLSUBSIDIO | P115: 0.02436 | Q115: 3000000 | R115: =IF(Q115<=Parametros!$B$4,Parametros!$B$3,0) -> 249095 | S115: =Q115*Parametros!$B$5 -> 120000 | T115: =Q115*Parametros!$B$6 -> 120000 | U115: =(Q115+R115)*Parametros!$B$10 -> 270757.92 | V115: =U115*Parametros!$B$11 -> 32490.95 | W115: =(Q115+R115)*Parametros!$B$12 -> 270757.92 | X115: =Q115*Parametros!$B$13 -> 125100 | Y115: =Q115*Parametros!$B$7 -> 255000 | Z115: =Q115*Parametros!$B$8 -> 360000 | AA115: =Q115*Parametros!$B$9 -> 120000 | AB115: =Q115*P115 -> 73080
A116: EMP-115 | B116: Cadena | C116: Marco | D116: M | E116: 30133 | F116: Soltero | G116: Bogotá D.C | H116: Bogotá | I116: AUXILIAR ADMINISTRATIVO | J116: 45929 | L116: FAMISANAR | M116: PROTECCION | N116: ARL SURA | O116: COLSUBSIDIO | P116: 0.00522 | Q116: 1750905 | R116: =IF(Q116<=Parametros!$B$4,Parametros!$B$3,0) -> 249095 | S116: =Q116*Parametros!$B$5 -> 70036.2 | T116: =Q116*Parametros!$B$6 -> 70036.2 | U116: =(Q116+R116)*Parametros!$B$10 -> 166666.67 | V116: =U116*Parametros!$B$11 -> 20000 | W116: =(Q116+R116)*Parametros!$B$12 -> 166666.67 | X116: =Q116*Parametros!$B$13 -> 73012.739 | Y116: =Q116*Parametros!$B$7 -> 148826.92 | Z116: =Q116*Parametros!$B$8 -> 210108.6 | AA116: =Q116*Parametros!$B$9 -> 70036.2 | AB116: =Q116*P116 -> 9139.7241
A117: EMP-116 | B117: Cadena | C117: Fernando | D117: M | E117: 32432 | F117: Soltero | G117: Bogotá D.C | H117: Bogotá | I117: JEFE DE MANTENIMIENTO | J117: 45945 | L117: SALUD TOTAL | M117: PORVENIR S.A. | N117: ARL SURA | O117: COLSUBSIDIO | P117: 0.0435 | Q117: 3200000 | R117: =IF(Q117<=Parametros!$B$4,Parametros!$B$3,0) -> 249095 | S117: =Q117*Parametros!$B$5 -> 128000 | T117: =Q117*Parametros!$B$6 -> 128000 | U117: =(Q117+R117)*Parametros!$B$10 -> 287424.58 | V117: =U117*Parametros!$B$11 -> 34490.95 | W117: =(Q117+R117)*Parametros!$B$12 -> 287424.58 | X117: =Q117*Parametros!$B$13 -> 133440 | Y117: =Q117*Parametros!$B$7 -> 272000 | Z117: =Q117*Parametros!$B$8 -> 384000 | AA117: =Q117*Parametros!$B$9 -> 128000 | AB117: =Q117*P117 -> 139200
A118: EMP-117 | B118: Bautista | C118: Viviana | D118: F | E118: 29627 | F118: Soltero | G118: Bogotá D.C | H118: Bogotá | I118: AUXILIAR ADMINISTRATIVO | J118: 46023 | L118: COMPENSAR EPS | M118: PORVENIR S.A. | N118: ARL SURA | O118: COLSUBSIDIO | P118: 0.00522 | Q118: 1750905 | R118: =IF(Q118<=Parametros!$B$4,Parametros!$B$3,0) -> 249095 | S118: =Q118*Parametros!$B$5 -> 70036.2 | T118: =Q118*Parametros!$B$6 -> 70036.2 | U118: =(Q118+R118)*Parametros!$B$10 -> 166666.67 | V118: =U118*Parametros!$B$11 -> 20000 | W118: =(Q118+R118)*Parametros!$B$12 -> 166666.67 | X118: =Q118*Parametros!$B$13 -> 73012.739 | Y118: =Q118*Parametros!$B$7 -> 148826.92 | Z118: =Q118*Parametros!$B$8 -> 210108.6 | AA118: =Q118*Parametros!$B$9 -> 70036.2 | AB118: =Q118*P118 -> 9139.7241
A119: EMP-118 | B119: Medina | C119: Viviana | D119: F | E119: 33198 | F119: Soltero | G119: Bogotá D.C | H119: Bogotá | I119: COORDINADOR DE FLOTA | J119: 43728 | L119: SANITAS | M119: PORVENIR S.A. | N119: ARL SURA | O119: COLSUBSIDIO | P119: 0.02436 | Q119: 3000000 | R119: =IF(Q119<=Parametros!$B$4,Parametros!$B$3,0) -> 249095 | S119: =Q119*Parametros!$B$5 -> 120000 | T119: =Q119*Parametros!$B$6 -> 120000 | U119: =(Q119+R119)*Parametros!$B$10 -> 270757.92 | V119: =U119*Parametros!$B$11 -> 32490.95 | W119: =(Q119+R119)*Parametros!$B$12 -> 270757.92 | X119: =Q119*Parametros!$B$13 -> 125100 | Y119: =Q119*Parametros!$B$7 -> 255000 | Z119: =Q119*Parametros!$B$8 -> 360000 | AA119: =Q119*Parametros!$B$9 -> 120000 | AB119: =Q119*P119 -> 73080
A120: EMP-119 | B120: Rojas | C120: Marcela | D120: F | E120: 31654 | F120: Soltero | G120: Bogotá D.C | H120: Bogotá | I120: ANALISTA DE RUTAS | J120: 43732 | L120: FAMISANAR | M120: COLPENSIONES | N120: ARL SURA | O120: COLSUBSIDIO | P120: 0.00522 | Q120: 1750905 | R120: =IF(Q120<=Parametros!$B$4,Parametros!$B$3,0) -> 249095 | S120: =Q120*Parametros!$B$5 -> 70036.2 | T120: =Q120*Parametros!$B$6 -> 70036.2 | U120: =(Q120+R120)*Parametros!$B$10 -> 166666.67 | V120: =U120*Parametros!$B$11 -> 20000 | W120: =(Q120+R120)*Parametros!$B$12 -> 166666.67 | X120: =Q120*Parametros!$B$13 -> 73012.739 | Y120: =Q120*Parametros!$B$7 -> 148826.92 | Z120: =Q120*Parametros!$B$8 -> 210108.6 | AA120: =Q120*Parametros!$B$9 -> 70036.2 | AB120: =Q120*P120 -> 9139.7241
A121: EMP-120 | B121: Aguirre | C121: Catalina | D121: F | E121: 27532 | F121: Soltero | G121: Bogotá D.C | H121: Bogotá | I121: CONDUCTOR | J121: 45383 | L121: SANITAS | M121: COLPENSIONES | N121: ARL SURA | O121: COLSUBSIDIO | P121: 0.0696 | Q121: 1900000 | R121: =IF(Q121<=Parametros!$B$4,Parametros!$B$3,0) -> 249095 | S121: =Q121*Parametros!$B$5 -> 76000 | T121: =Q121*Parametros!$B$6 -> 76000 | U121: =(Q121+R121)*Parametros!$B$10 -> 179091.25 | V121: =U121*Parametros!$B$11 -> 21490.95 | W121: =(Q121+R121)*Parametros!$B$12 -> 179091.25 | X121: =Q121*Parametros!$B$13 -> 79230 | Y121: =Q121*Parametros!$B$7 -> 161500 | Z121: =Q121*Parametros!$B$8 -> 228000 | AA121: =Q121*Parametros!$B$9 -> 76000 | AB121: =Q121*P121 -> 132240
...
